[
  {
    "timestamp_utc": "2025-07-18T19:57:36.812Z",
    "context_application_version": "1.2.68.528",
    "context_conn_country": "AR",
    "context_device_manufacturer": "LENOVO",
    "context_device_model": "20U4S4T000",
    "context_device_type": "desktop",
    "context_os_name": "windows",
    "context_os_version": "10.0.26100",
    "context_receiver_service_timestamp": 1752868677818,
    "context_time": 1752868656812,
    "message_episodes_num_added_audio": 0,
    "message_episodes_num_in_mdata": 4663,
    "message_episodes_num_missing_audio_id": 0,
    "message_episodes_num_parse_error": 0,
    "message_episodes_num_write_error": 0,
    "message_tracks_num_added_audio": 0,
    "message_tracks_num_in_mdata": 14070,
    "message_tracks_num_missing_audio_id": 0,
    "message_tracks_num_parse_error": 0,
    "message_tracks_num_write_error": 0
  },
  {
    "timestamp_utc": "2025-08-05T22:12:12.193Z",
    "context_application_version": "9.0.66.655",
    "context_conn_country": "AR",
    "context_device_manufacturer": "motorola",
    "context_device_model": "moto g72",
    "context_device_type": "mobile",
    "context_os_name": "android",
    "context_os_version": "13",
    "context_receiver_service_timestamp": 1754431931414,
    "context_time": 1754431932193,
    "message_episodes_num_added_audio": 0,
    "message_episodes_num_in_mdata": 7131,
    "message_episodes_num_missing_audio_id": 0,
    "message_episodes_num_parse_error": 0,
    "message_episodes_num_write_error": 0,
    "message_tracks_num_added_audio": 0,
    "message_tracks_num_in_mdata": 49987,
    "message_tracks_num_missing_audio_id": 0,
    "message_tracks_num_parse_error": 0,
    "message_tracks_num_write_error": 0
  },
  {
    "timestamp_utc": "2025-06-13T12:00:24.114Z",
    "context_application_version": "9.0.50.416",
    "context_conn_country": "AR",
    "context_device_manufacturer": "motorola",
    "context_device_model": "moto g72",
    "context_device_type": "mobile",
    "context_os_name": "android",
    "context_os_version": "13",
    "context_receiver_service_timestamp": 1749816035334,
    "context_time": 1749816024114,
    "message_episodes_num_added_audio": 0,
    "message_episodes_num_in_mdata": 6355,
    "message_episodes_num_missing_audio_id": 0,
    "message_episodes_num_parse_error": 0,
    "message_episodes_num_write_error": 0,
    "message_tracks_num_added_audio": 0,
    "message_tracks_num_in_mdata": 45397,
    "message_tracks_num_missing_audio_id": 0,
    "message_tracks_num_parse_error": 0,
    "message_tracks_num_write_error": 0
  },
  {
    "timestamp_utc": "2025-08-06T15:50:32.621Z",
    "context_application_version": "1.2.69.449",
    "context_conn_country": "AR",
    "context_device_manufacturer": "LENOVO",
    "context_device_model": "20U4S4T000",
    "context_device_type": "desktop",
    "context_os_name": "windows",
    "context_os_version": "10.0.26100",
    "context_receiver_service_timestamp": 1754495452820,
    "context_time": 1754495432621,
    "message_episodes_num_added_audio": 0,
    "message_episodes_num_in_mdata": 4665,
    "message_episodes_num_missing_audio_id": 0,
    "message_episodes_num_parse_error": 0,
    "message_episodes_num_write_error": 0,
    "message_tracks_num_added_audio": 0,
    "message_tracks_num_in_mdata": 14479,
    "message_tracks_num_missing_audio_id": 0,
    "message_tracks_num_parse_error": 0,
    "message_tracks_num_write_error": 0
  },
  {
    "timestamp_utc": "2025-07-29T20:11:32.948Z",
    "context_application_version": "1.2.68.528",
    "context_conn_country": "AR",
    "context_device_manufacturer": "LENOVO",
    "context_device_model": "20U4S4T000",
    "context_device_type": "desktop",
    "context_os_name": "windows",
    "context_os_version": "10.0.26100",
    "context_receiver_service_timestamp": 1753819913910,
    "context_time": 1753819892948,
    "message_episodes_num_added_audio": 2,
    "message_episodes_num_in_mdata": 4665,
    "message_episodes_num_missing_audio_id": 0,
    "message_episodes_num_parse_error": 0,
    "message_episodes_num_write_error": 0,
    "message_tracks_num_added_audio": 0,
    "message_tracks_num_in_mdata": 14409,
    "message_tracks_num_missing_audio_id": 0,
    "message_tracks_num_parse_error": 0,
    "message_tracks_num_write_error": 0
  },
  {
    "timestamp_utc": "2025-05-30T11:54:24.087Z",
    "context_application_version": "9.0.48.380",
    "context_conn_country": "AR",
    "context_device_manufacturer": "motorola",
    "context_device_model": "moto g72",
    "context_device_type": "mobile",
    "context_os_name": "android",
    "context_os_version": "13",
    "context_receiver_service_timestamp": 1748606075998,
    "context_time": 1748606064087,
    "message_episodes_num_added_audio": 0,
    "message_episodes_num_in_mdata": 6355,
    "message_episodes_num_missing_audio_id": 0,
    "message_episodes_num_parse_error": 0,
    "message_episodes_num_write_error": 0,
    "message_tracks_num_added_audio": 0,
    "message_tracks_num_in_mdata": 45299,
    "message_tracks_num_missing_audio_id": 0,
    "message_tracks_num_parse_error": 0,
    "message_tracks_num_write_error": 0
  },
  {
    "timestamp_utc": "2025-07-30T18:58:23.034Z",
    "context_application_version": "1.2.69.449",
    "context_conn_country": "AR",
    "context_device_manufacturer": "LENOVO",
    "context_device_model": "20U4S4T000",
    "context_device_type": "desktop",
    "context_os_name": "windows",
    "context_os_version": "10.0.26100",
    "context_receiver_service_timestamp": 1753901923760,
    "context_time": 1753901903034,
    "message_episodes_num_added_audio": 0,
    "message_episodes_num_in_mdata": 4665,
    "message_episodes_num_missing_audio_id": 0,
    "message_episodes_num_parse_error": 0,
    "message_episodes_num_write_error": 0,
    "message_tracks_num_added_audio": 0,
    "message_tracks_num_in_mdata": 14439,
    "message_tracks_num_missing_audio_id": 0,
    "message_tracks_num_parse_error": 0,
    "message_tracks_num_write_error": 0
  },
  {
    "timestamp_utc": "2025-05-30T14:52:52.615Z",
    "context_application_version": "1.2.63.394",
    "context_conn_country": "AR",
    "context_device_manufacturer": "LENOVO",
    "context_device_model": "20U4S4T000",
    "context_device_type": "desktop",
    "context_os_name": "windows",
    "context_os_version": "10.0.26100",
    "context_receiver_service_timestamp": 1748616797309,
    "context_time": 1748616772615,
    "message_episodes_num_added_audio": 0,
    "message_episodes_num_in_mdata": 3919,
    "message_episodes_num_missing_audio_id": 0,
    "message_episodes_num_parse_error": 0,
    "message_episodes_num_write_error": 0,
    "message_tracks_num_added_audio": 0,
    "message_tracks_num_in_mdata": 13600,
    "message_tracks_num_missing_audio_id": 0,
    "message_tracks_num_parse_error": 0,
    "message_tracks_num_write_error": 0
  },
  {
    "timestamp_utc": "2025-06-18T11:10:52.023Z",
    "context_application_version": "9.0.52.505",
    "context_conn_country": "AR",
    "context_device_manufacturer": "motorola",
    "context_device_model": "moto g72",
    "context_device_type": "mobile",
    "context_os_name": "android",
    "context_os_version": "13",
    "context_receiver_service_timestamp": 1750245064053,
    "context_time": 1750245052023,
    "message_episodes_num_added_audio": 0,
    "message_episodes_num_in_mdata": 6355,
    "message_episodes_num_missing_audio_id": 0,
    "message_episodes_num_parse_error": 0,
    "message_episodes_num_write_error": 0,
    "message_tracks_num_added_audio": 0,
    "message_tracks_num_in_mdata": 45446,
    "message_tracks_num_missing_audio_id": 0,
    "message_tracks_num_parse_error": 0,
    "message_tracks_num_write_error": 0
  },
  {
    "timestamp_utc": "2025-05-30T17:21:46.674Z",
    "context_application_version": "1.2.64.408",
    "context_conn_country": "AR",
    "context_device_manufacturer": "LENOVO",
    "context_device_model": "20U4S4T000",
    "context_device_type": "desktop",
    "context_os_name": "windows",
    "context_os_version": "10.0.26100",
    "context_receiver_service_timestamp": 1748625731326,
    "context_time": 1748625706674,
    "message_episodes_num_added_audio": 0,
    "message_episodes_num_in_mdata": 3919,
    "message_episodes_num_missing_audio_id": 0,
    "message_episodes_num_parse_error": 0,
    "message_episodes_num_write_error": 0,
    "message_tracks_num_added_audio": 0,
    "message_tracks_num_in_mdata": 13660,
    "message_tracks_num_missing_audio_id": 0,
    "message_tracks_num_parse_error": 0,
    "message_tracks_num_write_error": 0
  },
  {
    "timestamp_utc": "2025-05-18T14:38:56.426Z",
    "context_application_version": "9.0.44.478",
    "context_conn_country": "AR",
    "context_device_manufacturer": "motorola",
    "context_device_model": "moto g72",
    "context_device_type": "mobile",
    "context_os_name": "android",
    "context_os_version": "13",
    "context_receiver_service_timestamp": 1747579189830,
    "context_time": 1747579136426,
    "message_episodes_num_added_audio": 0,
    "message_episodes_num_in_mdata": 6353,
    "message_episodes_num_missing_audio_id": 0,
    "message_episodes_num_parse_error": 0,
    "message_episodes_num_write_error": 0,
    "message_tracks_num_added_audio": 0,
    "message_tracks_num_in_mdata": 42575,
    "message_tracks_num_missing_audio_id": 0,
    "message_tracks_num_parse_error": 0,
    "message_tracks_num_write_error": 0
  },
  {
    "timestamp_utc": "2025-06-23T17:05:54.054Z",
    "context_application_version": "1.2.64.408",
    "context_conn_country": "AR",
    "context_device_manufacturer": "LENOVO",
    "context_device_model": "20U4S4T000",
    "context_device_type": "desktop",
    "context_os_name": "windows",
    "context_os_version": "10.0.26100",
    "context_receiver_service_timestamp": 1750698376448,
    "context_time": 1750698354054,
    "message_episodes_num_added_audio": 3,
    "message_episodes_num_in_mdata": 3922,
    "message_episodes_num_missing_audio_id": 0,
    "message_episodes_num_parse_error": 0,
    "message_episodes_num_write_error": 0,
    "message_tracks_num_added_audio": 0,
    "message_tracks_num_in_mdata": 13886,
    "message_tracks_num_missing_audio_id": 0,
    "message_tracks_num_parse_error": 0,
    "message_tracks_num_write_error": 0
  },
  {
    "timestamp_utc": "2025-06-07T10:29:39.965Z",
    "context_application_version": "9.0.50.416",
    "context_conn_country": "AR",
    "context_device_manufacturer": "motorola",
    "context_device_model": "moto g72",
    "context_device_type": "mobile",
    "context_os_name": "android",
    "context_os_version": "13",
    "context_receiver_service_timestamp": 1749292191212,
    "context_time": 1749292179965,
    "message_episodes_num_added_audio": 0,
    "message_episodes_num_in_mdata": 6355,
    "message_episodes_num_missing_audio_id": 0,
    "message_episodes_num_parse_error": 0,
    "message_episodes_num_write_error": 0,
    "message_tracks_num_added_audio": 0,
    "message_tracks_num_in_mdata": 45356,
    "message_tracks_num_missing_audio_id": 0,
    "message_tracks_num_parse_error": 0,
    "message_tracks_num_write_error": 0
  },
  {
    "timestamp_utc": "2025-07-18T17:59:56.389Z",
    "context_application_version": "1.2.66.447",
    "context_conn_country": "AR",
    "context_device_manufacturer": "LENOVO",
    "context_device_model": "20U4S4T000",
    "context_device_type": "desktop",
    "context_os_name": "windows",
    "context_os_version": "10.0.26100",
    "context_receiver_service_timestamp": 1752861617853,
    "context_time": 1752861596389,
    "message_episodes_num_added_audio": 741,
    "message_episodes_num_in_mdata": 4663,
    "message_episodes_num_missing_audio_id": 0,
    "message_episodes_num_parse_error": 0,
    "message_episodes_num_write_error": 0,
    "message_tracks_num_added_audio": 0,
    "message_tracks_num_in_mdata": 14011,
    "message_tracks_num_missing_audio_id": 0,
    "message_tracks_num_parse_error": 0,
    "message_tracks_num_write_error": 0
  },
  {
    "timestamp_utc": "2025-06-05T12:05:28.412Z",
    "context_application_version": "9.0.50.416",
    "context_conn_country": "AR",
    "context_device_manufacturer": "motorola",
    "context_device_model": "moto g72",
    "context_device_type": "mobile",
    "context_os_name": "android",
    "context_os_version": "13",
    "context_receiver_service_timestamp": 1749125139655,
    "context_time": 1749125128412,
    "message_episodes_num_added_audio": 0,
    "message_episodes_num_in_mdata": 6355,
    "message_episodes_num_missing_audio_id": 0,
    "message_episodes_num_parse_error": 0,
    "message_episodes_num_write_error": 0,
    "message_tracks_num_added_audio": 0,
    "message_tracks_num_in_mdata": 45337,
    "message_tracks_num_missing_audio_id": 0,
    "message_tracks_num_parse_error": 0,
    "message_tracks_num_write_error": 0
  },
  {
    "timestamp_utc": "2025-05-20T20:16:58.510Z",
    "context_application_version": "9.0.44.478",
    "context_conn_country": "AR",
    "context_device_manufacturer": "motorola",
    "context_device_model": "moto g72",
    "context_device_type": "mobile",
    "context_os_name": "android",
    "context_os_version": "13",
    "context_receiver_service_timestamp": 1747772236846,
    "context_time": 1747772218510,
    "message_episodes_num_added_audio": 1,
    "message_episodes_num_in_mdata": 6354,
    "message_episodes_num_missing_audio_id": 0,
    "message_episodes_num_parse_error": 0,
    "message_episodes_num_write_error": 0,
    "message_tracks_num_added_audio": 0,
    "message_tracks_num_in_mdata": 42787,
    "message_tracks_num_missing_audio_id": 0,
    "message_tracks_num_parse_error": 0,
    "message_tracks_num_write_error": 0
  },
  {
    "timestamp_utc": "2025-06-30T14:30:37.405Z",
    "context_application_version": "1.2.66.447",
    "context_conn_country": "AR",
    "context_device_manufacturer": "LENOVO",
    "context_device_model": "20U4S4T000",
    "context_device_type": "desktop",
    "context_os_name": "windows",
    "context_os_version": "10.0.26100",
    "context_receiver_service_timestamp": 1751293860676,
    "context_time": 1751293837405,
    "message_episodes_num_added_audio": 0,
    "message_episodes_num_in_mdata": 3922,
    "message_episodes_num_missing_audio_id": 0,
    "message_episodes_num_parse_error": 0,
    "message_episodes_num_write_error": 0,
    "message_tracks_num_added_audio": 0,
    "message_tracks_num_in_mdata": 13927,
    "message_tracks_num_missing_audio_id": 0,
    "message_tracks_num_parse_error": 0,
    "message_tracks_num_write_error": 0
  },
  {
    "timestamp_utc": "2025-06-20T22:52:53.682Z",
    "context_application_version": "9.0.54.518",
    "context_conn_country": "AR",
    "context_device_manufacturer": "motorola",
    "context_device_model": "moto g72",
    "context_device_type": "mobile",
    "context_os_name": "android",
    "context_os_version": "13",
    "context_receiver_service_timestamp": 1750459985110,
    "context_time": 1750459973682,
    "message_episodes_num_added_audio": 4,
    "message_episodes_num_in_mdata": 6359,
    "message_episodes_num_missing_audio_id": 0,
    "message_episodes_num_parse_error": 0,
    "message_episodes_num_write_error": 0,
    "message_tracks_num_added_audio": 0,
    "message_tracks_num_in_mdata": 45459,
    "message_tracks_num_missing_audio_id": 0,
    "message_tracks_num_parse_error": 0,
    "message_tracks_num_write_error": 0
  },
  {
    "timestamp_utc": "2025-05-27T20:40:48.391Z",
    "context_application_version": "9.0.46.496",
    "context_conn_country": "AR",
    "context_device_manufacturer": "motorola",
    "context_device_model": "moto g72",
    "context_device_type": "mobile",
    "context_os_name": "android",
    "context_os_version": "13",
    "context_receiver_service_timestamp": 1748378818752,
    "context_time": 1748378448391,
    "message_episodes_num_added_audio": 1,
    "message_episodes_num_in_mdata": 6355,
    "message_episodes_num_missing_audio_id": 0,
    "message_episodes_num_parse_error": 0,
    "message_episodes_num_write_error": 0,
    "message_tracks_num_added_audio": 0,
    "message_tracks_num_in_mdata": 45295,
    "message_tracks_num_missing_audio_id": 0,
    "message_tracks_num_parse_error": 0,
    "message_tracks_num_write_error": 0
  },
  {
    "timestamp_utc": "2025-06-08T15:17:12.720Z",
    "context_application_version": "9.0.50.416",
    "context_conn_country": "AR",
    "context_device_manufacturer": "motorola",
    "context_device_model": "moto g72",
    "context_device_type": "mobile",
    "context_os_name": "android",
    "context_os_version": "13",
    "context_receiver_service_timestamp": 1749395844773,
    "context_time": 1749395832720,
    "message_episodes_num_added_audio": 0,
    "message_episodes_num_in_mdata": 6355,
    "message_episodes_num_missing_audio_id": 0,
    "message_episodes_num_parse_error": 0,
    "message_episodes_num_write_error": 0,
    "message_tracks_num_added_audio": 0,
    "message_tracks_num_in_mdata": 45364,
    "message_tracks_num_missing_audio_id": 0,
    "message_tracks_num_parse_error": 0,
    "message_tracks_num_write_error": 0
  },
  {
    "timestamp_utc": "2025-07-20T01:29:26.716Z",
    "context_application_version": "9.0.62.622",
    "context_conn_country": "BR",
    "context_device_manufacturer": "motorola",
    "context_device_model": "moto g72",
    "context_device_type": "mobile",
    "context_os_name": "android",
    "context_os_version": "13",
    "context_receiver_service_timestamp": 1752996706355,
    "context_time": 1752974966716,
    "message_episodes_num_added_audio": 7,
    "message_episodes_num_in_mdata": 7131,
    "message_episodes_num_missing_audio_id": 0,
    "message_episodes_num_parse_error": 0,
    "message_episodes_num_write_error": 0,
    "message_tracks_num_added_audio": 0,
    "message_tracks_num_in_mdata": 47594,
    "message_tracks_num_missing_audio_id": 0,
    "message_tracks_num_parse_error": 0,
    "message_tracks_num_write_error": 0
  },
  {
    "timestamp_utc": "2025-05-16T11:50:17.636Z",
    "context_application_version": "9.0.44.478",
    "context_conn_country": "AR",
    "context_device_manufacturer": "motorola",
    "context_device_model": "moto g72",
    "context_device_type": "mobile",
    "context_os_name": "android",
    "context_os_version": "13",
    "context_receiver_service_timestamp": 1747396234065,
    "context_time": 1747396217636,
    "message_episodes_num_added_audio": 0,
    "message_episodes_num_in_mdata": 6353,
    "message_episodes_num_missing_audio_id": 0,
    "message_episodes_num_parse_error": 0,
    "message_episodes_num_write_error": 0,
    "message_tracks_num_added_audio": 0,
    "message_tracks_num_in_mdata": 42514,
    "message_tracks_num_missing_audio_id": 0,
    "message_tracks_num_parse_error": 0,
    "message_tracks_num_write_error": 0
  },
  {
    "timestamp_utc": "2025-06-29T10:04:28.230Z",
    "context_application_version": "9.0.56.591",
    "context_conn_country": "AR",
    "context_device_manufacturer": "motorola",
    "context_device_model": "moto g72",
    "context_device_type": "mobile",
    "context_os_name": "android",
    "context_os_version": "13",
    "context_receiver_service_timestamp": 1751203420068,
    "context_time": 1751191468230,
    "message_episodes_num_added_audio": 0,
    "message_episodes_num_in_mdata": 6360,
    "message_episodes_num_missing_audio_id": 0,
    "message_episodes_num_parse_error": 0,
    "message_episodes_num_write_error": 0,
    "message_tracks_num_added_audio": 0,
    "message_tracks_num_in_mdata": 45514,
    "message_tracks_num_missing_audio_id": 0,
    "message_tracks_num_parse_error": 0,
    "message_tracks_num_write_error": 0
  },
  {
    "timestamp_utc": "2025-08-08T15:07:18.688Z",
    "context_application_version": "1.2.69.449",
    "context_conn_country": "AR",
    "context_device_manufacturer": "LENOVO",
    "context_device_model": "20U4S4T000",
    "context_device_type": "desktop",
    "context_os_name": "windows",
    "context_os_version": "10.0.26100",
    "context_receiver_service_timestamp": 1754665657347,
    "context_time": 1754665638688,
    "message_episodes_num_added_audio": 0,
    "message_episodes_num_in_mdata": 4665,
    "message_episodes_num_missing_audio_id": 0,
    "message_episodes_num_parse_error": 0,
    "message_episodes_num_write_error": 0,
    "message_tracks_num_added_audio": 0,
    "message_tracks_num_in_mdata": 14484,
    "message_tracks_num_missing_audio_id": 0,
    "message_tracks_num_parse_error": 0,
    "message_tracks_num_write_error": 0
  },
  {
    "timestamp_utc": "2025-07-20T04:13:15.751Z",
    "context_application_version": "9.0.62.622",
    "context_conn_country": "BR",
    "context_device_manufacturer": "motorola",
    "context_device_model": "moto g72",
    "context_device_type": "mobile",
    "context_os_name": "android",
    "context_os_version": "13",
    "context_receiver_service_timestamp": 1752996710175,
    "context_time": 1752984795751,
    "message_episodes_num_added_audio": 0,
    "message_episodes_num_in_mdata": 7131,
    "message_episodes_num_missing_audio_id": 0,
    "message_episodes_num_parse_error": 0,
    "message_episodes_num_write_error": 0,
    "message_tracks_num_added_audio": 0,
    "message_tracks_num_in_mdata": 47594,
    "message_tracks_num_missing_audio_id": 0,
    "message_tracks_num_parse_error": 0,
    "message_tracks_num_write_error": 0
  },
  {
    "timestamp_utc": "2025-07-12T12:46:35.601Z",
    "context_application_version": "9.0.60.614",
    "context_conn_country": "AR",
    "context_device_manufacturer": "motorola",
    "context_device_model": "moto g72",
    "context_device_type": "mobile",
    "context_os_name": "android",
    "context_os_version": "13",
    "context_receiver_service_timestamp": 1752324400291,
    "context_time": 1752324395601,
    "message_episodes_num_added_audio": 772,
    "message_episodes_num_in_mdata": 7124,
    "message_episodes_num_missing_audio_id": 0,
    "message_episodes_num_parse_error": 0,
    "message_episodes_num_write_error": 0,
    "message_tracks_num_added_audio": 0,
    "message_tracks_num_in_mdata": 47445,
    "message_tracks_num_missing_audio_id": 0,
    "message_tracks_num_parse_error": 0,
    "message_tracks_num_write_error": 0
  },
  {
    "timestamp_utc": "2025-06-06T11:37:15.116Z",
    "context_application_version": "9.0.50.416",
    "context_conn_country": "AR",
    "context_device_manufacturer": "motorola",
    "context_device_model": "moto g72",
    "context_device_type": "mobile",
    "context_os_name": "android",
    "context_os_version": "13",
    "context_receiver_service_timestamp": 1749209846666,
    "context_time": 1749209835116,
    "message_episodes_num_added_audio": 0,
    "message_episodes_num_in_mdata": 6355,
    "message_episodes_num_missing_audio_id": 0,
    "message_episodes_num_parse_error": 0,
    "message_episodes_num_write_error": 0,
    "message_tracks_num_added_audio": 0,
    "message_tracks_num_in_mdata": 45339,
    "message_tracks_num_missing_audio_id": 0,
    "message_tracks_num_parse_error": 0,
    "message_tracks_num_write_error": 0
  },
  {
    "timestamp_utc": "2025-07-19T13:57:48.865Z",
    "context_application_version": "1.2.68.528",
    "context_conn_country": "AR",
    "context_device_manufacturer": "LENOVO",
    "context_device_model": "20U4S4T000",
    "context_device_type": "desktop",
    "context_os_name": "windows",
    "context_os_version": "10.0.26100",
    "context_receiver_service_timestamp": 1752933489968,
    "context_time": 1752933468865,
    "message_episodes_num_added_audio": 0,
    "message_episodes_num_in_mdata": 4663,
    "message_episodes_num_missing_audio_id": 0,
    "message_episodes_num_parse_error": 0,
    "message_episodes_num_write_error": 0,
    "message_tracks_num_added_audio": 0,
    "message_tracks_num_in_mdata": 14073,
    "message_tracks_num_missing_audio_id": 0,
    "message_tracks_num_parse_error": 0,
    "message_tracks_num_write_error": 0
  },
  {
    "timestamp_utc": "2025-06-08T21:00:08.659Z",
    "context_application_version": "9.0.50.416",
    "context_conn_country": "AR",
    "context_device_manufacturer": "motorola",
    "context_device_model": "moto g72",
    "context_device_type": "mobile",
    "context_os_name": "android",
    "context_os_version": "13",
    "context_receiver_service_timestamp": 1749416421055,
    "context_time": 1749416408659,
    "message_episodes_num_added_audio": 0,
    "message_episodes_num_in_mdata": 6355,
    "message_episodes_num_missing_audio_id": 0,
    "message_episodes_num_parse_error": 0,
    "message_episodes_num_write_error": 0,
    "message_tracks_num_added_audio": 0,
    "message_tracks_num_in_mdata": 45369,
    "message_tracks_num_missing_audio_id": 0,
    "message_tracks_num_parse_error": 0,
    "message_tracks_num_write_error": 0
  },
  {
    "timestamp_utc": "2025-06-28T16:50:48.599Z",
    "context_application_version": "9.0.56.591",
    "context_conn_country": "AR",
    "context_device_manufacturer": "motorola",
    "context_device_model": "moto g72",
    "context_device_type": "mobile",
    "context_os_name": "android",
    "context_os_version": "13",
    "context_receiver_service_timestamp": 1751129459672,
    "context_time": 1751129448599,
    "message_episodes_num_added_audio": 0,
    "message_episodes_num_in_mdata": 6360,
    "message_episodes_num_missing_audio_id": 0,
    "message_episodes_num_parse_error": 0,
    "message_episodes_num_write_error": 0,
    "message_tracks_num_added_audio": 0,
    "message_tracks_num_in_mdata": 45511,
    "message_tracks_num_missing_audio_id": 0,
    "message_tracks_num_parse_error": 0,
    "message_tracks_num_write_error": 0
  },
  {
    "timestamp_utc": "2025-06-21T12:46:47.396Z",
    "context_application_version": "9.0.54.518",
    "context_conn_country": "AR",
    "context_device_manufacturer": "motorola",
    "context_device_model": "moto g72",
    "context_device_type": "mobile",
    "context_os_name": "android",
    "context_os_version": "13",
    "context_receiver_service_timestamp": 1750510019754,
    "context_time": 1750510007396,
    "message_episodes_num_added_audio": 0,
    "message_episodes_num_in_mdata": 6359,
    "message_episodes_num_missing_audio_id": 0,
    "message_episodes_num_parse_error": 0,
    "message_episodes_num_write_error": 0,
    "message_tracks_num_added_audio": 0,
    "message_tracks_num_in_mdata": 45505,
    "message_tracks_num_missing_audio_id": 0,
    "message_tracks_num_parse_error": 0,
    "message_tracks_num_write_error": 0
  },
  {
    "timestamp_utc": "2025-05-31T12:31:14.842Z",
    "context_application_version": "9.0.48.380",
    "context_conn_country": "AR",
    "context_device_manufacturer": "motorola",
    "context_device_model": "moto g72",
    "context_device_type": "mobile",
    "context_os_name": "android",
    "context_os_version": "13",
    "context_receiver_service_timestamp": 1748694685725,
    "context_time": 1748694674842,
    "message_episodes_num_added_audio": 0,
    "message_episodes_num_in_mdata": 6355,
    "message_episodes_num_missing_audio_id": 0,
    "message_episodes_num_parse_error": 0,
    "message_episodes_num_write_error": 0,
    "message_tracks_num_added_audio": 0,
    "message_tracks_num_in_mdata": 45330,
    "message_tracks_num_missing_audio_id": 0,
    "message_tracks_num_parse_error": 0,
    "message_tracks_num_write_error": 0
  }
]