[
  {
    "message_candidate_uris": [
      "spotify:artist:0du5cEVh5yTK9QJze8zA0C",
      "spotify:track:2plbrEY59IikOBgBGLjaoe",
      "spotify:playlist:5PQJnqvGTMX5rjR8c7GIkq",
      "spotify:playlist:37i9dQZF1DZ06evO03DwPK",
      "spotify:playlist:37i9dQZF1E4vTHVDH1FT3Y",
      "spotify:track:5vNRhkKd0yEAg8suGBpjeY",
      "spotify:track:32OlwWuMpZ6b0aN2RZOeMS",
      "spotify:track:3w3y8KPTfNeOKPiqUTakBh",
      "spotify:artist:3fMbdgg4jU18AjLCKBhRSm",
      "spotify:track:6b8Be6ljOzmkOmFslEb23P",
      "spotify:track:4pryE6cN2gFL1FVF5fYINl",
      "spotify:artist:4gzpq5DPGxSnKTe4SA8HAU",
      "spotify:artist:1HY2Jd0NmPuamShAr6KMms",
      "spotify:playlist:474jn2a57cASJtV2HBpwbx",
      "spotify:track:0nJW01T7XtvILxQgC5J7Wh",
      "spotify:track:4mOWnjz30frv1pKMM6DNfv",
      "spotify:search:bruno+mars",
      "spotify:search:bruno+mars+lady+gaga",
      "spotify:search:bruno+mars+exitos",
      "spotify:search:bruno+mars+playlist"
    ],
    "message_query": "Bruno mars",
    "timestamp_utc": "2025-08-09T21:03:04.405Z",
    "context_time": 1754773384405,
    "message_country": "AR",
    "message_locale": "en_GB",
    "message_platform": "ANDROID_ARM",
    "message_timestamp": 1754773385172,
    "message_top_recs_uris": [
    ],
    "message_user_agent": "Spotify/9.0.68.632 Android/33 (moto g72)"
  },
  {
    "message_candidate_uris": [
      "spotify:playlist:1msY3c9fzgE3V11aNhsq2O",
      "spotify:playlist:2bairK0EAgiZy6W2tjw2UV",
      "spotify:playlist:1OC997aDTD3Ji5ZybaV7LV",
      "spotify:playlist:3KWKH0BUvYMEbp2zgOD2l5",
      "spotify:playlist:0XdBQNUf7Ng39W2g5hkYvP",
      "spotify:track:6TZcRzevpjY6lbwg0RbghV",
      "spotify:playlist:36EVuywkYuJLsQfOZ2HU4X",
      "spotify:playlist:1JnTKPkNcVfpJMGF6fhZ1h",
      "spotify:playlist:1hEdFWtYe5PmxNQKlUJWzL",
      "spotify:playlist:2TIvNr191G0VJ9Cdmi4A8u",
      "spotify:playlist:0WmbfhNdbVSp9Qqb3GM3FT",
      "spotify:playlist:5tMKU5suWbT7QWpjIzsflA",
      "spotify:episode:1r6rhiURJD9IJuYz5G2HQ8",
      "spotify:playlist:2JkyMySXLTMabws8ZTkzMJ",
      "spotify:playlist:78xhpWhXna83q0CCkyouaJ",
      "spotify:track:6RzcNTnS02dnqoQMdTkQwi",
      "spotify:search:brasil+2025",
      "spotify:search:brasil+2025+as+melhores+e+mais+tocadas",
      "spotify:search:brasil+2024",
      "spotify:search:brasil+2024+funk+pop+latin+150+bpm"
    ],
    "message_query": "Brasil 2025",
    "timestamp_utc": "2025-07-25T21:44:24.548Z",
    "context_time": 1753479864548,
    "message_country": "AR",
    "message_locale": "en_GB",
    "message_platform": "ANDROID_ARM",
    "message_timestamp": 1753479863554,
    "message_top_recs_uris": [
    ],
    "message_user_agent": "Spotify/9.0.64.608 Android/33 (moto g72)"
  },
  {
    "message_candidate_uris": [
      "spotify:artist:26dSoYclwsYLMAKD3tpOr4",
      "spotify:playlist:37i9dQZF1DZ06evO1bSHqE",
      "spotify:playlist:3IRQehF2IhLczR9kyKDYVA",
      "spotify:playlist:4UloqXLVxIKJgCNbtWaf69",
      "spotify:playlist:0ikAq4EgRbrgbjSPIgjS8l",
      "spotify:playlist:7yPUOBJQIUVQa3uxx1qnuy",
      "spotify:episode:2Oxgf4xieZofBdhkICbhYp",
      "spotify:artist:0du5cEVh5yTK9QJze8zA0C",
      "spotify:playlist:1OC997aDTD3Ji5ZybaV7LV",
      "spotify:track:1KdwPeY1WRWQGHCmRJTveb",
      "spotify:track:0COqiPhxzoWICwFCS4eZcp",
      "spotify:artist:3Z02hBLubJxuFJfhacLSDc",
      "spotify:track:42T2QQv3xgBlpQxaSP7lnK",
      "spotify:artist:3eqjTLE0HfPfh78zjh6TqT",
      "spotify:playlist:1s4xuWqdyImOY6vvOb1oow",
      "spotify:track:5cZqsjVs6MevCnAkasbEOX",
      "spotify:search:brasil",
      "spotify:search:britney+spears",
      "spotify:search:bruce+springsteen",
      "spotify:search:bruno+mars"
    ],
    "message_query": "br",
    "timestamp_utc": "2025-07-25T21:44:21.290Z",
    "context_time": 1753479861290,
    "message_country": "AR",
    "message_locale": "en_GB",
    "message_platform": "ANDROID_ARM",
    "message_timestamp": 1753479860356,
    "message_top_recs_uris": [
    ],
    "message_user_agent": "Spotify/9.0.64.608 Android/33 (moto g72)"
  },
  {
    "message_candidate_uris": [
      "spotify:artist:0du5cEVh5yTK9QJze8zA0C",
      "spotify:track:2plbrEY59IikOBgBGLjaoe",
      "spotify:track:32OlwWuMpZ6b0aN2RZOeMS",
      "spotify:episode:09NOJuCMy7XRIN0oR6zL5D",
      "spotify:playlist:37i9dQZF1DZ06evO03DwPK",
      "spotify:playlist:37i9dQZF1E4vTHVDH1FT3Y",
      "spotify:playlist:5PQJnqvGTMX5rjR8c7GIkq",
      "spotify:artist:3fMbdgg4jU18AjLCKBhRSm",
      "spotify:track:3w3y8KPTfNeOKPiqUTakBh",
      "spotify:playlist:474jn2a57cASJtV2HBpwbx",
      "spotify:track:6b8Be6ljOzmkOmFslEb23P",
      "spotify:artist:6M2wZ9GZgrQXHCFfjv46we",
      "spotify:playlist:6x59Uuh8xp32g88XiCiNLY",
      "spotify:track:386RUes7n1uM1yfzgeUuwp",
      "spotify:artist:04gDigrS5kc9YWfZHwBETP",
      "spotify:track:0nJW01T7XtvILxQgC5J7Wh",
      "spotify:search:bruno+mars",
      "spotify:search:bruno+mars+lady+gaga",
      "spotify:search:bruno+mars+exitos",
      "spotify:search:bruno+marrone"
    ],
    "message_query": "Bruno ma",
    "timestamp_utc": "2025-08-09T21:03:03.687Z",
    "context_time": 1754773383687,
    "message_country": "AR",
    "message_locale": "en_GB",
    "message_platform": "ANDROID_ARM",
    "message_timestamp": 1754773384511,
    "message_top_recs_uris": [
    ],
    "message_user_agent": "Spotify/9.0.68.632 Android/33 (moto g72)"
  },
  {
    "message_candidate_uris": [
      "spotify:track:0zZnBbRW4Dt4cJKVtUQFwF",
      "spotify:artist:7MiDcPa6UiV3In7lIM71IN",
      "spotify:playlist:1OC997aDTD3Ji5ZybaV7LV",
      "spotify:track:0INaMqjJJe1BZpnWuCxDzt",
      "spotify:playlist:2PY7eEcSWukU56dgHdz771",
      "spotify:show:2792nUA5mbbiL3ZWeeAiyl",
      "spotify:playlist:2TIvNr191G0VJ9Cdmi4A8u",
      "spotify:playlist:30Z5afhQY1bz0ONmO76DGB",
      "spotify:playlist:1hEdFWtYe5PmxNQKlUJWzL",
      "spotify:track:1XdVkLDSTk6cM3SEP5v8Bs",
      "spotify:playlist:0cTxwGHW2gQMU6ZKS9xC0h",
      "spotify:playlist:7G7s5q3FV37QoCYTilmNwM",
      "spotify:track:36SJ7ZFx8J1f1RsewmUwMX",
      "spotify:playlist:1QY3gV9Ihkz8FBTpNbfVxC",
      "spotify:artist:1QOmebWGB6FdFtW7Bo3F0W",
      "spotify:track:3ac2SnHk4KYjP2Au4ZL7eu",
      "spotify:search:gustavo+lima",
      "spotify:search:gusttavo+lima",
      "spotify:search:gusttavo+lima+balada+tch%C3%AA+tcherere+tch%C3%AA+tch%C3%AA+gustavo+lima",
      "spotify:search:gusttavo+lima+balada+ao+vivo"
    ],
    "message_query": "Gustavo li",
    "timestamp_utc": "2025-07-25T21:44:05.584Z",
    "context_time": 1753479845584,
    "message_country": "AR",
    "message_locale": "en_GB",
    "message_platform": "ANDROID_ARM",
    "message_timestamp": 1753479844614,
    "message_top_recs_uris": [
    ],
    "message_user_agent": "Spotify/9.0.64.608 Android/33 (moto g72)"
  },
  {
    "message_candidate_uris": [
      "spotify:artist:4bthk9UfsYUYdcFyqxmSUU",
      "spotify:artist:1eClJfHLoDI4rZe5HxzBFv",
      "spotify:track:1GjbTNFImFrjFsNdleDe78",
      "spotify:artist:762310PdDnwsDxAQxzQkfX",
      "spotify:playlist:2rdKNmH41lScn5r4zxcYrK",
      "spotify:playlist:6y9k6f5YOTijehDfWocohw",
      "spotify:track:67Hna13dNDkZvBpTXRIaOJ",
      "spotify:playlist:37i9dQZF1E4mViRxNOaVVW",
      "spotify:artist:0lZoBs4Pzo7R89JM9lxwoT",
      "spotify:track:7w6PJe5KBPyvuRYxFkPssC",
      "spotify:playlist:37i9dQZF1DZ06evO2rEeYg",
      "spotify:playlist:0GmOUDpkM8XcrhBZ1mjamV",
      "spotify:track:4RvWPyQ5RL0ao9LPZeSouE",
      "spotify:artist:6FXMGgJwohJLUSr5nVlf9X",
      "spotify:artist:2jzc5TC5TVFLXQlBNiIUzE",
      "spotify:track:1XYHqSfJK9ud9nuRjQcbXi",
      "spotify:search:tears+for+fears",
      "spotify:search:tears+in+heaven",
      "spotify:search:teardrop",
      "spotify:search:tear+drop"
    ],
    "message_query": "tear",
    "timestamp_utc": "2025-08-09T15:34:24.933Z",
    "context_time": 1754753664933,
    "message_country": "AR",
    "message_locale": "en_GB",
    "message_platform": "ANDROID_ARM",
    "message_timestamp": 1754753665740,
    "message_top_recs_uris": [
    ],
    "message_user_agent": "Spotify/9.0.68.632 Android/33 (moto g72)"
  },
  {
    "message_candidate_uris": [
      "spotify:artist:7MiDcPa6UiV3In7lIM71IN",
      "spotify:track:0zZnBbRW4Dt4cJKVtUQFwF",
      "spotify:playlist:1OC997aDTD3Ji5ZybaV7LV",
      "spotify:track:0INaMqjJJe1BZpnWuCxDzt",
      "spotify:artist:6NRf8By2aUKxzKzi2eqr7z",
      "spotify:episode:4FT9OBLv857D5GfUghcf2C",
      "spotify:playlist:2PY7eEcSWukU56dgHdz771",
      "spotify:playlist:37i9dQZF1DZ06evO12BIac",
      "spotify:artist:1MYBiThgwAJGvoX74eCv5J",
      "spotify:playlist:1hEdFWtYe5PmxNQKlUJWzL",
      "spotify:playlist:37i9dQZF1E4nc6r5XLZ1Yu",
      "spotify:playlist:30Z5afhQY1bz0ONmO76DGB",
      "spotify:playlist:2TIvNr191G0VJ9Cdmi4A8u",
      "spotify:playlist:0cTxwGHW2gQMU6ZKS9xC0h",
      "spotify:playlist:3APf3LJ3lC9ka35T9dJfba",
      "spotify:playlist:79PD8EX840RmPqEVNf8xgj",
      "spotify:search:gustavo+lima",
      "spotify:search:gusttavo+lima",
      "spotify:search:gusttavo+lima+balada+ao+vivo",
      "spotify:search:gustavo+cerati"
    ],
    "message_query": "Gustavo l",
    "timestamp_utc": "2025-07-25T21:39:08.388Z",
    "context_time": 1753479548388,
    "message_country": "AR",
    "message_locale": "en_GB",
    "message_platform": "ANDROID_ARM",
    "message_timestamp": 1753479547327,
    "message_top_recs_uris": [
    ],
    "message_user_agent": "Spotify/9.0.64.608 Android/33 (moto g72)"
  },
  {
    "message_candidate_uris": [
      "spotify:artist:0du5cEVh5yTK9QJze8zA0C",
      "spotify:track:2plbrEY59IikOBgBGLjaoe",
      "spotify:playlist:37i9dQZF1DZ06evO03DwPK",
      "spotify:track:32OlwWuMpZ6b0aN2RZOeMS",
      "spotify:playlist:5PQJnqvGTMX5rjR8c7GIkq",
      "spotify:episode:09NOJuCMy7XRIN0oR6zL5D",
      "spotify:playlist:37i9dQZF1E4vTHVDH1FT3Y",
      "spotify:artist:3fMbdgg4jU18AjLCKBhRSm",
      "spotify:track:3w3y8KPTfNeOKPiqUTakBh",
      "spotify:playlist:474jn2a57cASJtV2HBpwbx",
      "spotify:artist:4gzpq5DPGxSnKTe4SA8HAU",
      "spotify:playlist:6x59Uuh8xp32g88XiCiNLY",
      "spotify:track:6b8Be6ljOzmkOmFslEb23P",
      "spotify:artist:1HY2Jd0NmPuamShAr6KMms",
      "spotify:track:7DSAEUvxU8FajXtRloy8M0",
      "spotify:track:386RUes7n1uM1yfzgeUuwp",
      "spotify:search:bruno+mars",
      "spotify:search:bruno+mars+lady+gaga",
      "spotify:search:bruno+mars+exitos",
      "spotify:search:bruno+mars+up"
    ],
    "message_query": "Bruno m",
    "timestamp_utc": "2025-08-09T21:03:03.213Z",
    "context_time": 1754773383213,
    "message_country": "AR",
    "message_locale": "en_GB",
    "message_platform": "ANDROID_ARM",
    "message_timestamp": 1754773384062,
    "message_top_recs_uris": [
    ],
    "message_user_agent": "Spotify/9.0.68.632 Android/33 (moto g72)"
  },
  {
    "message_candidate_uris": [
      "spotify:artist:7MiDcPa6UiV3In7lIM71IN",
      "spotify:track:0zZnBbRW4Dt4cJKVtUQFwF",
      "spotify:playlist:1OC997aDTD3Ji5ZybaV7LV",
      "spotify:track:0INaMqjJJe1BZpnWuCxDzt",
      "spotify:artist:6NRf8By2aUKxzKzi2eqr7z",
      "spotify:episode:4FT9OBLv857D5GfUghcf2C",
      "spotify:playlist:2PY7eEcSWukU56dgHdz771",
      "spotify:playlist:37i9dQZF1DZ06evO12BIac",
      "spotify:artist:1MYBiThgwAJGvoX74eCv5J",
      "spotify:playlist:1hEdFWtYe5PmxNQKlUJWzL",
      "spotify:playlist:37i9dQZF1E4nc6r5XLZ1Yu",
      "spotify:playlist:30Z5afhQY1bz0ONmO76DGB",
      "spotify:playlist:2TIvNr191G0VJ9Cdmi4A8u",
      "spotify:playlist:0cTxwGHW2gQMU6ZKS9xC0h",
      "spotify:playlist:3APf3LJ3lC9ka35T9dJfba",
      "spotify:playlist:79PD8EX840RmPqEVNf8xgj",
      "spotify:search:gustavo+lima",
      "spotify:search:gusttavo+lima",
      "spotify:search:gusttavo+lima+balada+ao+vivo",
      "spotify:search:gustavo+cerati"
    ],
    "message_query": "Gustavo l",
    "timestamp_utc": "2025-07-25T21:44:05.533Z",
    "context_time": 1753479845533,
    "message_country": "AR",
    "message_locale": "en_GB",
    "message_platform": "ANDROID_ARM",
    "message_timestamp": 1753479844422,
    "message_top_recs_uris": [
    ],
    "message_user_agent": "Spotify/9.0.64.608 Android/33 (moto g72)"
  },
  {
    "message_candidate_uris": [
      "spotify:artist:4bthk9UfsYUYdcFyqxmSUU",
      "spotify:playlist:2rdKNmH41lScn5r4zxcYrK",
      "spotify:artist:1eClJfHLoDI4rZe5HxzBFv",
      "spotify:artist:762310PdDnwsDxAQxzQkfX",
      "spotify:artist:2ycnb8Er79LoH2AsR5ldjh",
      "spotify:playlist:6y9k6f5YOTijehDfWocohw",
      "spotify:track:7w6PJe5KBPyvuRYxFkPssC",
      "spotify:track:1GjbTNFImFrjFsNdleDe78",
      "spotify:track:4RvWPyQ5RL0ao9LPZeSouE",
      "spotify:playlist:37i9dQZF1DZ06evO2rEeYg",
      "spotify:playlist:37i9dQZF1E4mViRxNOaVVW",
      "spotify:playlist:0GmOUDpkM8XcrhBZ1mjamV",
      "spotify:track:1kgdslQYmeTR4thk9whoRw",
      "spotify:artist:0lZoBs4Pzo7R89JM9lxwoT",
      "spotify:artist:6hN9F0iuULZYWXppob22Aj",
      "spotify:artist:2jzc5TC5TVFLXQlBNiIUzE",
      "spotify:search:tears+for+fears",
      "spotify:search:tears+in+heaven",
      "spotify:search:tears+for+fears+greatest+hits",
      "spotify:search:teardrop"
    ],
    "message_query": "tears",
    "timestamp_utc": "2025-08-09T15:34:25.302Z",
    "context_time": 1754753665302,
    "message_country": "AR",
    "message_locale": "en_GB",
    "message_platform": "ANDROID_ARM",
    "message_timestamp": 1754753666120,
    "message_top_recs_uris": [
    ],
    "message_user_agent": "Spotify/9.0.68.632 Android/33 (moto g72)"
  },
  {
    "message_candidate_uris": [
      "spotify:artist:0du5cEVh5yTK9QJze8zA0C",
      "spotify:track:2plbrEY59IikOBgBGLjaoe",
      "spotify:artist:5JXhkyafynxCvxtov7C1PV",
      "spotify:artist:3tDix7cw0fgoa5idDGJ6Wo",
      "spotify:track:5vNRhkKd0yEAg8suGBpjeY",
      "spotify:artist:59OheJsvimLlXWvuL9j7Df",
      "spotify:track:32OlwWuMpZ6b0aN2RZOeMS",
      "spotify:playlist:5PQJnqvGTMX5rjR8c7GIkq",
      "spotify:playlist:37i9dQZF1E4vTHVDH1FT3Y",
      "spotify:playlist:37i9dQZF1DZ06evO03DwPK",
      "spotify:artist:3fMbdgg4jU18AjLCKBhRSm",
      "spotify:episode:09NOJuCMy7XRIN0oR6zL5D",
      "spotify:artist:4gzpq5DPGxSnKTe4SA8HAU",
      "spotify:playlist:474jn2a57cASJtV2HBpwbx",
      "spotify:track:3w3y8KPTfNeOKPiqUTakBh",
      "spotify:artist:04gDigrS5kc9YWfZHwBETP",
      "spotify:search:bruno+mars",
      "spotify:search:bruno+mars+lady+gaga",
      "spotify:search:bruno+arias",
      "spotify:search:bruno+mars+exitos"
    ],
    "message_query": "Bruno ",
    "timestamp_utc": "2025-08-09T21:03:03.030Z",
    "context_time": 1754773383030,
    "message_country": "AR",
    "message_locale": "en_GB",
    "message_platform": "ANDROID_ARM",
    "message_timestamp": 1754773383827,
    "message_top_recs_uris": [
    ],
    "message_user_agent": "Spotify/9.0.68.632 Android/33 (moto g72)"
  },
  {
    "message_candidate_uris": [
      "spotify:artist:5M52tdBnJaKSvOpJGz8mfZ",
      "spotify:artist:2F9pvj94b52wGKs0OqiNi2",
      "spotify:artist:7MhMgCo0Bl0Kukl93PZbYS",
      "spotify:artist:7lzordPuZEXxwt9aoVZYmG",
      "spotify:playlist:0X6Zymo0ssqDoBinB6zycC",
      "spotify:artist:6FBDaR13swtiWwGhX1WQsP",
      "spotify:artist:58lV9VcRSjABbAbfWS6skp",
      "spotify:artist:5rSXSAkZ67PYJSvpUpkOr7",
      "spotify:playlist:37i9dQZF1DZ06evO1wTz9u",
      "spotify:artist:2QsynagSdAqZj3U9HgDzjD",
      "spotify:artist:26dSoYclwsYLMAKD3tpOr4",
      "spotify:artist:6MxyNXnnmwQwdW2PD0gXYO",
      "spotify:show:3u26tlz7A3WyWRtXliX9a9",
      "spotify:playlist:0Doz4CruAk3llXzq9DiQKZ",
      "spotify:playlist:7lQBND0S5d8rWk0UHwxBVq",
      "spotify:playlist:1e9vygQafzHuSo2h1RRv5y",
      "spotify:search:black+sabbath",
      "spotify:search:babasonicos",
      "spotify:search:backstreet+boys",
      "spotify:search:bob+marley+the+wailers"
    ],
    "message_query": "b",
    "timestamp_utc": "2025-08-09T21:03:01.470Z",
    "context_time": 1754773381470,
    "message_country": "AR",
    "message_locale": "en_GB",
    "message_platform": "ANDROID_ARM",
    "message_timestamp": 1754773382238,
    "message_top_recs_uris": [
    ],
    "message_user_agent": "Spotify/9.0.68.632 Android/33 (moto g72)"
  },
  {
    "message_candidate_uris": [
      "spotify:artist:1QOmebWGB6FdFtW7Bo3F0W",
      "spotify:playlist:37i9dQZF1DZ06evO12BIac",
      "spotify:playlist:3APf3LJ3lC9ka35T9dJfba",
      "spotify:playlist:37i9dQZF1E4nc6r5XLZ1Yu",
      "spotify:artist:3dOfwznaY7FEKpF8aw1q9i",
      "spotify:track:5wjiZSbxaLyLpGimpwqh1H",
      "spotify:track:1Bov4bMY1IgfOrvUWWbhSe",
      "spotify:track:65DBZofI0b79kfHTcWWDuU",
      "spotify:album:2rIdWbXPjcq8K7BCccBhhC",
      "spotify:playlist:3JlgQTTJxoWQ5nNOVdsBqf",
      "spotify:album:51wepZm3YvZfvFxiu7D5F8",
      "spotify:playlist:2wys4K71I3F6C4puwKImHK",
      "spotify:album:46Yq9oqsaZJb9ahoMk9iVd",
      "spotify:playlist:2TieOXUFdPe8OrB8WYgKJy",
      "spotify:album:75onhE4ne52iMHlVcpHUKR",
      "spotify:playlist:37i9dQZF1EIZwLDpPbvfRp",
      "spotify:search:gustavo+cerati",
      "spotify:search:gustavo+cordera",
      "spotify:search:gustavo+pena",
      "spotify:search:gustavo+pena+el+pr%C3%ADncipe"
    ],
    "message_query": "Gustavo ",
    "timestamp_utc": "2025-07-25T21:44:03.689Z",
    "context_time": 1753479843689,
    "message_country": "AR",
    "message_locale": "en_GB",
    "message_platform": "ANDROID_ARM",
    "message_timestamp": 1753479842687,
    "message_top_recs_uris": [
    ],
    "message_user_agent": "Spotify/9.0.64.608 Android/33 (moto g72)"
  },
  {
    "message_candidate_uris": [
      "spotify:artist:1QOmebWGB6FdFtW7Bo3F0W",
      "spotify:playlist:37i9dQZF1DZ06evO12BIac",
      "spotify:playlist:3APf3LJ3lC9ka35T9dJfba",
      "spotify:playlist:37i9dQZF1E4nc6r5XLZ1Yu",
      "spotify:episode:00Rekhmq5k49h7Ku731lrY",
      "spotify:artist:3dOfwznaY7FEKpF8aw1q9i",
      "spotify:album:51wepZm3YvZfvFxiu7D5F8",
      "spotify:playlist:37i9dQZF1DZ06evO4uy2je",
      "spotify:album:46Yq9oqsaZJb9ahoMk9iVd",
      "spotify:playlist:37i9dQZF1EIZwLDpPbvfRp",
      "spotify:album:2rIdWbXPjcq8K7BCccBhhC",
      "spotify:artist:7An4yvF7hDYDolN4m5zKBp",
      "spotify:track:5wjiZSbxaLyLpGimpwqh1H",
      "spotify:playlist:2TieOXUFdPe8OrB8WYgKJy",
      "spotify:track:65DBZofI0b79kfHTcWWDuU",
      "spotify:track:1Bov4bMY1IgfOrvUWWbhSe",
      "spotify:search:gustavo+cerati",
      "spotify:search:gustavo+cordera",
      "spotify:search:gustavo+pena",
      "spotify:search:gustavo+pena+el+pr%C3%ADncipe"
    ],
    "message_query": "gust",
    "timestamp_utc": "2025-07-25T21:39:08.201Z",
    "context_time": 1753479548201,
    "message_country": "AR",
    "message_locale": "en_GB",
    "message_platform": "ANDROID_ARM",
    "message_timestamp": 1753479546199,
    "message_top_recs_uris": [
    ],
    "message_user_agent": "Spotify/9.0.64.608 Android/33 (moto g72)"
  },
  {
    "message_candidate_uris": [
      "spotify:artist:4bthk9UfsYUYdcFyqxmSUU",
      "spotify:playlist:5wmDhgfCHkBkauknSfOc6h",
      "spotify:artist:2UazAtjfzqBF0Nho2awK4z",
      "spotify:artist:33qOK5uJ8AR2xuQQAhHump",
      "spotify:playlist:2rdKNmH41lScn5r4zxcYrK",
      "spotify:playlist:6vFVELx5jVVWgvLU74FI2Q",
      "spotify:show:7wQ5NNrWVmC7wDE9Y7cbwR",
      "spotify:playlist:18YQJfsyCTJMmcq18LgDWY",
      "spotify:playlist:3y9xLOBoZxrCVCrOcC9zif",
      "spotify:playlist:55UbLUvaj3mghe8BHwag5u",
      "spotify:artist:3SUT1jjM5hzZj9TLfLZGIP",
      "spotify:artist:4ZDoy7AWNgQVmX7T0u0B1j",
      "spotify:artist:28hJdGN1Awf7u3ifk2lVkg",
      "spotify:track:2kMVxFh1y5gow2hBtqGO4m",
      "spotify:playlist:5tkmp4FQqwVfCSia1pNKVu",
      "spotify:playlist:7bNKrNBfnPLG3ANBbVn5mB",
      "spotify:search:teddy+swims",
      "spotify:search:techno",
      "spotify:search:temones",
      "spotify:search:tears"
    ],
    "message_query": "te",
    "timestamp_utc": "2025-08-09T15:34:24.359Z",
    "context_time": 1754753664359,
    "message_country": "AR",
    "message_locale": "en_GB",
    "message_platform": "ANDROID_ARM",
    "message_timestamp": 1754753665138,
    "message_top_recs_uris": [
    ],
    "message_user_agent": "Spotify/9.0.68.632 Android/33 (moto g72)"
  },
  {
    "message_candidate_uris": [
      "spotify:artist:1QOmebWGB6FdFtW7Bo3F0W",
      "spotify:playlist:37i9dQZF1DZ06evO12BIac",
      "spotify:artist:3qm84nBOXUEQ2vnTfUTTFC",
      "spotify:playlist:3APf3LJ3lC9ka35T9dJfba",
      "spotify:playlist:37i9dQZF1E4nc6r5XLZ1Yu",
      "spotify:artist:7An4yvF7hDYDolN4m5zKBp",
      "spotify:playlist:37i9dQZF1EIZwLDpPbvfRp",
      "spotify:episode:5W5BzLHx0gkzfkCLohnIGP",
      "spotify:album:46Yq9oqsaZJb9ahoMk9iVd",
      "spotify:album:51wepZm3YvZfvFxiu7D5F8",
      "spotify:artist:3dOfwznaY7FEKpF8aw1q9i",
      "spotify:album:2rIdWbXPjcq8K7BCccBhhC",
      "spotify:track:5wjiZSbxaLyLpGimpwqh1H",
      "spotify:playlist:2TieOXUFdPe8OrB8WYgKJy",
      "spotify:playlist:2wys4K71I3F6C4puwKImHK",
      "spotify:track:1Bov4bMY1IgfOrvUWWbhSe",
      "spotify:search:gustavo+cerati",
      "spotify:search:gustavo+cordera",
      "spotify:search:gustavo+pena+el+pr%C3%ADncipe",
      "spotify:search:gustavo+pena"
    ],
    "message_query": "gus",
    "timestamp_utc": "2025-07-25T21:39:08.184Z",
    "context_time": 1753479548184,
    "message_country": "AR",
    "message_locale": "en_GB",
    "message_platform": "ANDROID_ARM",
    "message_timestamp": 1753479546001,
    "message_top_recs_uris": [
    ],
    "message_user_agent": "Spotify/9.0.64.608 Android/33 (moto g72)"
  },
  {
    "message_candidate_uris": [
      "spotify:playlist:37i9dQZF1DZ06evO3oYXfO",
      "spotify:artist:5M52tdBnJaKSvOpJGz8mfZ",
      "spotify:show:0VZhTvcOW02bPW8uGGFAhN",
      "spotify:artist:2F9pvj94b52wGKs0OqiNi2",
      "spotify:playlist:37i9dQZF1DZ06evO1wTz9u",
      "spotify:artist:78SHxLdtysAXgywQ4vE0Oa",
      "spotify:artist:7MhMgCo0Bl0Kukl93PZbYS",
      "spotify:playlist:7lQBND0S5d8rWk0UHwxBVq",
      "spotify:track:3zKe52aokhDkP1Fi4pzGPq",
      "spotify:track:1QFh8OH1e78dGd3VyJZCAC",
      "spotify:artist:7lzordPuZEXxwt9aoVZYmG",
      "spotify:track:0tZ3mElWcr74OOhKEiNz1x",
      "spotify:track:2EoOZnxNgtmZaD8uUmz2nD",
      "spotify:playlist:0Doz4CruAk3llXzq9DiQKZ",
      "spotify:artist:58lV9VcRSjABbAbfWS6skp",
      "spotify:playlist:1e9vygQafzHuSo2h1RRv5y",
      "spotify:search:black+sabbath",
      "spotify:search:babasonicos",
      "spotify:search:bush",
      "spotify:search:billy+idol"
    ],
    "message_query": "b",
    "timestamp_utc": "2025-07-25T21:44:21.048Z",
    "context_time": 1753479861048,
    "message_country": "AR",
    "message_locale": "en_GB",
    "message_platform": "ANDROID_ARM",
    "message_timestamp": 1753479860123,
    "message_top_recs_uris": [
    ],
    "message_user_agent": "Spotify/9.0.64.608 Android/33 (moto g72)"
  },
  {
    "message_candidate_uris": [
      "spotify:playlist:1msY3c9fzgE3V11aNhsq2O",
      "spotify:playlist:2bairK0EAgiZy6W2tjw2UV",
      "spotify:playlist:37i9dQZF1DWZ2DWnNKZTXs",
      "spotify:playlist:1OC997aDTD3Ji5ZybaV7LV",
      "spotify:playlist:3m1ar1Cz9v7JJqFVP6HNXT",
      "spotify:episode:08EatLv4j9Zf2mwBdGttfu",
      "spotify:playlist:1hEdFWtYe5PmxNQKlUJWzL",
      "spotify:playlist:0WmbfhNdbVSp9Qqb3GM3FT",
      "spotify:playlist:37i9dQZEVXbMXbN3EUUhlg",
      "spotify:playlist:2TIvNr191G0VJ9Cdmi4A8u",
      "spotify:playlist:3b1OB14lWIMPHDQ2Rvjtme",
      "spotify:track:36SJ7ZFx8J1f1RsewmUwMX",
      "spotify:playlist:36EVuywkYuJLsQfOZ2HU4X",
      "spotify:playlist:0XdBQNUf7Ng39W2g5hkYvP",
      "spotify:track:6i2kn3iS5WKzsaYBdeHLIQ",
      "spotify:track:1PCvKFPWnTXAe2oaReVUcr",
      "spotify:search:brasil+2025",
      "spotify:search:brasil+2025+as+melhores+e+mais+tocadas",
      "spotify:search:brasilerass+famosas",
      "spotify:search:brasil+2014"
    ],
    "message_query": "Brasil 2",
    "timestamp_utc": "2025-07-25T21:44:23.325Z",
    "context_time": 1753479863325,
    "message_country": "AR",
    "message_locale": "en_GB",
    "message_platform": "ANDROID_ARM",
    "message_timestamp": 1753479862414,
    "message_top_recs_uris": [
    ],
    "message_user_agent": "Spotify/9.0.64.608 Android/33 (moto g72)"
  },
  {
    "message_candidate_uris": [
      "spotify:artist:1QOmebWGB6FdFtW7Bo3F0W",
      "spotify:playlist:37i9dQZF1DZ06evO12BIac",
      "spotify:playlist:3APf3LJ3lC9ka35T9dJfba",
      "spotify:playlist:37i9dQZF1E4nc6r5XLZ1Yu",
      "spotify:episode:00Rekhmq5k49h7Ku731lrY",
      "spotify:artist:3dOfwznaY7FEKpF8aw1q9i",
      "spotify:album:51wepZm3YvZfvFxiu7D5F8",
      "spotify:playlist:37i9dQZF1DZ06evO4uy2je",
      "spotify:album:46Yq9oqsaZJb9ahoMk9iVd",
      "spotify:playlist:37i9dQZF1EIZwLDpPbvfRp",
      "spotify:album:2rIdWbXPjcq8K7BCccBhhC",
      "spotify:artist:7An4yvF7hDYDolN4m5zKBp",
      "spotify:track:5wjiZSbxaLyLpGimpwqh1H",
      "spotify:playlist:2TieOXUFdPe8OrB8WYgKJy",
      "spotify:track:65DBZofI0b79kfHTcWWDuU",
      "spotify:track:1Bov4bMY1IgfOrvUWWbhSe",
      "spotify:search:gustavo+cerati",
      "spotify:search:gustavo+cordera",
      "spotify:search:gustavo+pena",
      "spotify:search:gustavo+pena+el+pr%C3%ADncipe"
    ],
    "message_query": "gust",
    "timestamp_utc": "2025-07-25T21:44:03.328Z",
    "context_time": 1753479843328,
    "message_country": "AR",
    "message_locale": "en_GB",
    "message_platform": "ANDROID_ARM",
    "message_timestamp": 1753479842450,
    "message_top_recs_uris": [
    ],
    "message_user_agent": "Spotify/9.0.64.608 Android/33 (moto g72)"
  },
  {
    "message_candidate_uris": [
      "spotify:track:0zZnBbRW4Dt4cJKVtUQFwF",
      "spotify:artist:7MiDcPa6UiV3In7lIM71IN",
      "spotify:playlist:1OC997aDTD3Ji5ZybaV7LV",
      "spotify:track:0INaMqjJJe1BZpnWuCxDzt",
      "spotify:playlist:2PY7eEcSWukU56dgHdz771",
      "spotify:playlist:30Z5afhQY1bz0ONmO76DGB",
      "spotify:playlist:2TIvNr191G0VJ9Cdmi4A8u",
      "spotify:playlist:1hEdFWtYe5PmxNQKlUJWzL",
      "spotify:playlist:6mhvyCK6HBrmyytACxGs9r",
      "spotify:playlist:37i9dQZF1E4vyndvGUp4dP",
      "spotify:track:1XdVkLDSTk6cM3SEP5v8Bs",
      "spotify:playlist:1QY3gV9Ihkz8FBTpNbfVxC",
      "spotify:track:36SJ7ZFx8J1f1RsewmUwMX",
      "spotify:track:6xepovPqjvrkEw9Y5AMmTm",
      "spotify:playlist:0cTxwGHW2gQMU6ZKS9xC0h",
      "spotify:playlist:01kCJyJWmoyIlIU2LUlxGf",
      "spotify:search:gustavo+lima",
      "spotify:search:gusttavo+lima",
      "spotify:search:gusttavo+lima+balada+tch%C3%AA+tcherere+tch%C3%AA+tch%C3%AA+gustavo+lima",
      "spotify:search:gusttavo+lima+balada+ao+vivo"
    ],
    "message_query": "Gustavo lim",
    "timestamp_utc": "2025-07-25T21:39:08.690Z",
    "context_time": 1753479548690,
    "message_country": "AR",
    "message_locale": "en_GB",
    "message_platform": "ANDROID_ARM",
    "message_timestamp": 1753479547764,
    "message_top_recs_uris": [
    ],
    "message_user_agent": "Spotify/9.0.64.608 Android/33 (moto g72)"
  },
  {
    "message_candidate_uris": [
      "spotify:artist:3qm84nBOXUEQ2vnTfUTTFC",
      "spotify:playlist:37i9dQZF1DZ06evO1Ziym4",
      "spotify:artist:1QOmebWGB6FdFtW7Bo3F0W",
      "spotify:playlist:37i9dQZF1DZ06evO1rzScc",
      "spotify:playlist:22LgD7bUoQLvSRy322OxNp",
      "spotify:playlist:37i9dQZF1DZ06evO12BIac",
      "spotify:episode:1lFvSSkO4VDPVUK7AwGQBQ",
      "spotify:playlist:61AuftDk6G9CV0t1OuHAEc",
      "spotify:playlist:5htTCXmpYg3czvFZXIQkrP",
      "spotify:playlist:2ZONg885GRx1XlgcsNVzLk",
      "spotify:track:2yoPmaL4ckJ5CI6oRtLEir",
      "spotify:playlist:7bsHHU5RGk9L1ifUKc8PeD",
      "spotify:playlist:3edtw06fcs0gDxWX7jyTCn",
      "spotify:playlist:3APf3LJ3lC9ka35T9dJfba",
      "spotify:playlist:4jmjLUUxvtSgHi4JZCctHU",
      "spotify:artist:2wjmZuSHtRx96Qxb8HiP2o",
      "spotify:search:guns+n%27+roses",
      "spotify:search:guasones",
      "spotify:search:gustavo+cerati",
      "spotify:search:guaracha"
    ],
    "message_query": "gu",
    "timestamp_utc": "2025-07-25T21:39:08.196Z",
    "context_time": 1753479548196,
    "message_country": "AR",
    "message_locale": "en_GB",
    "message_platform": "ANDROID_ARM",
    "message_timestamp": 1753479545728,
    "message_top_recs_uris": [
    ],
    "message_user_agent": "Spotify/9.0.64.608 Android/33 (moto g72)"
  },
  {
    "message_candidate_uris": [
      "spotify:artist:26dSoYclwsYLMAKD3tpOr4",
      "spotify:artist:3Z02hBLubJxuFJfhacLSDc",
      "spotify:artist:0du5cEVh5yTK9QJze8zA0C",
      "spotify:artist:3eqjTLE0HfPfh78zjh6TqT",
      "spotify:playlist:0ikAq4EgRbrgbjSPIgjS8l",
      "spotify:playlist:3IRQehF2IhLczR9kyKDYVA",
      "spotify:episode:4yFOjZDPmdSqrLy0mqdjXP",
      "spotify:playlist:4UloqXLVxIKJgCNbtWaf69",
      "spotify:playlist:7yPUOBJQIUVQa3uxx1qnuy",
      "spotify:playlist:37i9dQZF1DZ06evO1bSHqE",
      "spotify:artist:1Ffb6ejR6Fe5IamqA5oRUF",
      "spotify:playlist:1OC997aDTD3Ji5ZybaV7LV",
      "spotify:artist:5RNFFojXkPRmlJZIwXeKQC",
      "spotify:playlist:1s4xuWqdyImOY6vvOb1oow",
      "spotify:artist:0VKh7CQDi9MkUvaBMoK1V0",
      "spotify:playlist:1hEdFWtYe5PmxNQKlUJWzL",
      "spotify:search:brasil",
      "spotify:search:bruno+mars",
      "spotify:search:bryan+adams",
      "spotify:search:britney+spears"
    ],
    "message_query": "br",
    "timestamp_utc": "2025-08-09T21:03:01.725Z",
    "context_time": 1754773381725,
    "message_country": "AR",
    "message_locale": "en_GB",
    "message_platform": "ANDROID_ARM",
    "message_timestamp": 1754773382569,
    "message_top_recs_uris": [
    ],
    "message_user_agent": "Spotify/9.0.68.632 Android/33 (moto g72)"
  },
  {
    "message_candidate_uris": [
      "spotify:track:0zZnBbRW4Dt4cJKVtUQFwF",
      "spotify:artist:7MiDcPa6UiV3In7lIM71IN",
      "spotify:playlist:1OC997aDTD3Ji5ZybaV7LV",
      "spotify:track:0INaMqjJJe1BZpnWuCxDzt",
      "spotify:playlist:2PY7eEcSWukU56dgHdz771",
      "spotify:show:2792nUA5mbbiL3ZWeeAiyl",
      "spotify:playlist:2TIvNr191G0VJ9Cdmi4A8u",
      "spotify:playlist:30Z5afhQY1bz0ONmO76DGB",
      "spotify:playlist:1hEdFWtYe5PmxNQKlUJWzL",
      "spotify:track:1XdVkLDSTk6cM3SEP5v8Bs",
      "spotify:playlist:0cTxwGHW2gQMU6ZKS9xC0h",
      "spotify:playlist:7G7s5q3FV37QoCYTilmNwM",
      "spotify:track:36SJ7ZFx8J1f1RsewmUwMX",
      "spotify:playlist:1QY3gV9Ihkz8FBTpNbfVxC",
      "spotify:artist:1QOmebWGB6FdFtW7Bo3F0W",
      "spotify:track:3ac2SnHk4KYjP2Au4ZL7eu",
      "spotify:search:gustavo+lima",
      "spotify:search:gusttavo+lima",
      "spotify:search:gusttavo+lima+balada+tch%C3%AA+tcherere+tch%C3%AA+tch%C3%AA+gustavo+lima",
      "spotify:search:gusttavo+lima+balada+ao+vivo"
    ],
    "message_query": "Gustavo li",
    "timestamp_utc": "2025-07-25T21:39:08.596Z",
    "context_time": 1753479548596,
    "message_country": "AR",
    "message_locale": "en_GB",
    "message_platform": "ANDROID_ARM",
    "message_timestamp": 1753479547545,
    "message_top_recs_uris": [
    ],
    "message_user_agent": "Spotify/9.0.64.608 Android/33 (moto g72)"
  },
  {
    "message_candidate_uris": [
      "spotify:playlist:1msY3c9fzgE3V11aNhsq2O",
      "spotify:playlist:2bairK0EAgiZy6W2tjw2UV",
      "spotify:playlist:37i9dQZEVXbMXbN3EUUhlg",
      "spotify:playlist:1OC997aDTD3Ji5ZybaV7LV",
      "spotify:playlist:3KWKH0BUvYMEbp2zgOD2l5",
      "spotify:playlist:0WmbfhNdbVSp9Qqb3GM3FT",
      "spotify:playlist:0XdBQNUf7Ng39W2g5hkYvP",
      "spotify:playlist:1hEdFWtYe5PmxNQKlUJWzL",
      "spotify:playlist:36EVuywkYuJLsQfOZ2HU4X",
      "spotify:playlist:5Rm0ORL1NVK3bpvYDtVrVV",
      "spotify:episode:1r6rhiURJD9IJuYz5G2HQ8",
      "spotify:playlist:2TIvNr191G0VJ9Cdmi4A8u",
      "spotify:playlist:1hVm9JyKcKH2OXP2IW9Wsg",
      "spotify:playlist:4ipzd3LgVnZrSGPeyV3cbz",
      "spotify:track:6TZcRzevpjY6lbwg0RbghV",
      "spotify:track:36SJ7ZFx8J1f1RsewmUwMX",
      "spotify:search:brasil+2025",
      "spotify:search:brasil+2025+as+melhores+e+mais+tocadas",
      "spotify:search:brasilerass+famosas",
      "spotify:search:brasil+2024"
    ],
    "message_query": "Brasil 202",
    "timestamp_utc": "2025-07-25T21:44:24.274Z",
    "context_time": 1753479864274,
    "message_country": "AR",
    "message_locale": "en_GB",
    "message_platform": "ANDROID_ARM",
    "message_timestamp": 1753479863183,
    "message_top_recs_uris": [
    ],
    "message_user_agent": "Spotify/9.0.64.608 Android/33 (moto g72)"
  },
  {
    "message_candidate_uris": [
      "spotify:playlist:1OC997aDTD3Ji5ZybaV7LV",
      "spotify:playlist:37i9dQZEVXbMXbN3EUUhlg",
      "spotify:artist:3Z02hBLubJxuFJfhacLSDc",
      "spotify:playlist:1hEdFWtYe5PmxNQKlUJWzL",
      "spotify:playlist:0XdBQNUf7Ng39W2g5hkYvP",
      "spotify:playlist:2TIvNr191G0VJ9Cdmi4A8u",
      "spotify:show:6Y0jzPbjaj0jXmkfIFfDtP",
      "spotify:playlist:6bA0D4xJJ8zQPEs26YnzMb",
      "spotify:track:36SJ7ZFx8J1f1RsewmUwMX",
      "spotify:playlist:74N8rGDKzlNFoXSJasm7YS",
      "spotify:track:0c27qjzqEgMLMnWTl5bCU8",
      "spotify:track:2iDDnYmaz1HhedjI91fbmp",
      "spotify:album:2lIZef4lzdvZkiiCzvPKj7",
      "spotify:playlist:0cTxwGHW2gQMU6ZKS9xC0h",
      "spotify:artist:168dgYui7ExaU612eooDF1",
      "spotify:playlist:37i9dQZF1DWSBxfQH2VCQH",
      "spotify:search:brasil",
      "spotify:search:brasilerass+famosas",
      "spotify:search:brasilero",
      "spotify:search:brazilian+music"
    ],
    "message_query": "bra",
    "timestamp_utc": "2025-07-25T21:44:21.420Z",
    "context_time": 1753479861420,
    "message_country": "AR",
    "message_locale": "en_GB",
    "message_platform": "ANDROID_ARM",
    "message_timestamp": 1753479860571,
    "message_top_recs_uris": [
    ],
    "message_user_agent": "Spotify/9.0.64.608 Android/33 (moto g72)"
  },
  {
    "message_candidate_uris": [
      "spotify:artist:1QOmebWGB6FdFtW7Bo3F0W",
      "spotify:playlist:37i9dQZF1DZ06evO12BIac",
      "spotify:playlist:3APf3LJ3lC9ka35T9dJfba",
      "spotify:artist:3qm84nBOXUEQ2vnTfUTTFC",
      "spotify:playlist:37i9dQZF1E4nc6r5XLZ1Yu",
      "spotify:artist:7An4yvF7hDYDolN4m5zKBp",
      "spotify:playlist:37i9dQZF1EIZwLDpPbvfRp",
      "spotify:episode:5W5BzLHx0gkzfkCLohnIGP",
      "spotify:album:46Yq9oqsaZJb9ahoMk9iVd",
      "spotify:album:51wepZm3YvZfvFxiu7D5F8",
      "spotify:artist:3dOfwznaY7FEKpF8aw1q9i",
      "spotify:album:2rIdWbXPjcq8K7BCccBhhC",
      "spotify:track:5wjiZSbxaLyLpGimpwqh1H",
      "spotify:playlist:2TieOXUFdPe8OrB8WYgKJy",
      "spotify:playlist:2wys4K71I3F6C4puwKImHK",
      "spotify:track:1Bov4bMY1IgfOrvUWWbhSe",
      "spotify:search:gustavo+cerati",
      "spotify:search:gustavo+cordera",
      "spotify:search:gustavo+pena+el+pr%C3%ADncipe",
      "spotify:search:gustavo+pena"
    ],
    "message_query": "gus",
    "timestamp_utc": "2025-07-25T21:44:02.951Z",
    "context_time": 1753479842951,
    "message_country": "AR",
    "message_locale": "en_GB",
    "message_platform": "ANDROID_ARM",
    "message_timestamp": 1753479842066,
    "message_top_recs_uris": [
    ],
    "message_user_agent": "Spotify/9.0.64.608 Android/33 (moto g72)"
  },
  {
    "message_candidate_uris": [
      "spotify:track:0zZnBbRW4Dt4cJKVtUQFwF",
      "spotify:artist:7MiDcPa6UiV3In7lIM71IN",
      "spotify:playlist:1OC997aDTD3Ji5ZybaV7LV",
      "spotify:track:0INaMqjJJe1BZpnWuCxDzt",
      "spotify:playlist:2PY7eEcSWukU56dgHdz771",
      "spotify:playlist:30Z5afhQY1bz0ONmO76DGB",
      "spotify:playlist:2TIvNr191G0VJ9Cdmi4A8u",
      "spotify:playlist:1hEdFWtYe5PmxNQKlUJWzL",
      "spotify:playlist:6mhvyCK6HBrmyytACxGs9r",
      "spotify:playlist:37i9dQZF1E4vyndvGUp4dP",
      "spotify:track:1XdVkLDSTk6cM3SEP5v8Bs",
      "spotify:playlist:1QY3gV9Ihkz8FBTpNbfVxC",
      "spotify:track:36SJ7ZFx8J1f1RsewmUwMX",
      "spotify:track:6xepovPqjvrkEw9Y5AMmTm",
      "spotify:playlist:0cTxwGHW2gQMU6ZKS9xC0h",
      "spotify:playlist:01kCJyJWmoyIlIU2LUlxGf",
      "spotify:search:gustavo+lima",
      "spotify:search:gusttavo+lima",
      "spotify:search:gusttavo+lima+balada+tch%C3%AA+tcherere+tch%C3%AA+tch%C3%AA+gustavo+lima",
      "spotify:search:gusttavo+lima+balada+ao+vivo"
    ],
    "message_query": "Gustavo lim",
    "timestamp_utc": "2025-07-25T21:44:05.758Z",
    "context_time": 1753479845758,
    "message_country": "AR",
    "message_locale": "en_GB",
    "message_platform": "ANDROID_ARM",
    "message_timestamp": 1753479844845,
    "message_top_recs_uris": [
    ],
    "message_user_agent": "Spotify/9.0.64.608 Android/33 (moto g72)"
  },
  {
    "message_candidate_uris": [
      "spotify:artist:4bthk9UfsYUYdcFyqxmSUU",
      "spotify:playlist:2rdKNmH41lScn5r4zxcYrK",
      "spotify:show:4jCktQ3R1F78kO58JHvsaf",
      "spotify:artist:6CwDvApcRshxhEVMP30Sq7",
      "spotify:playlist:6y9k6f5YOTijehDfWocohw",
      "spotify:track:1GjbTNFImFrjFsNdleDe78",
      "spotify:playlist:37i9dQZF1E4mViRxNOaVVW",
      "spotify:playlist:37i9dQZF1DZ06evO2rEeYg",
      "spotify:track:7w6PJe5KBPyvuRYxFkPssC",
      "spotify:playlist:0GmOUDpkM8XcrhBZ1mjamV",
      "spotify:track:67Hna13dNDkZvBpTXRIaOJ",
      "spotify:track:4RvWPyQ5RL0ao9LPZeSouE",
      "spotify:artist:31eXqCx5cAlItdGdoHMEOu",
      "spotify:playlist:37i9dQZF1E8UfqZeOB2SyE",
      "spotify:playlist:37i9dQZF1EIVOW9mgbYgVF",
      "spotify:track:1kgdslQYmeTR4thk9whoRw",
      "spotify:search:tears+for+fears",
      "spotify:search:tears+in+heaven",
      "spotify:search:teardrop",
      "spotify:search:tears"
    ],
    "message_query": "tea",
    "timestamp_utc": "2025-08-09T15:34:24.607Z",
    "context_time": 1754753664607,
    "message_country": "AR",
    "message_locale": "en_GB",
    "message_platform": "ANDROID_ARM",
    "message_timestamp": 1754753665390,
    "message_top_recs_uris": [
    ],
    "message_user_agent": "Spotify/9.0.68.632 Android/33 (moto g72)"
  },
  {
    "message_candidate_uris": [
      "spotify:artist:0du5cEVh5yTK9QJze8zA0C",
      "spotify:track:2plbrEY59IikOBgBGLjaoe",
      "spotify:track:5vNRhkKd0yEAg8suGBpjeY",
      "spotify:episode:09NOJuCMy7XRIN0oR6zL5D",
      "spotify:playlist:37i9dQZF1DZ06evO03DwPK",
      "spotify:playlist:5PQJnqvGTMX5rjR8c7GIkq",
      "spotify:playlist:37i9dQZF1E4vTHVDH1FT3Y",
      "spotify:track:32OlwWuMpZ6b0aN2RZOeMS",
      "spotify:artist:3fMbdgg4jU18AjLCKBhRSm",
      "spotify:artist:59OheJsvimLlXWvuL9j7Df",
      "spotify:artist:3tDix7cw0fgoa5idDGJ6Wo",
      "spotify:artist:4gzpq5DPGxSnKTe4SA8HAU",
      "spotify:artist:5JXhkyafynxCvxtov7C1PV",
      "spotify:artist:1HY2Jd0NmPuamShAr6KMms",
      "spotify:artist:04gDigrS5kc9YWfZHwBETP",
      "spotify:playlist:474jn2a57cASJtV2HBpwbx",
      "spotify:search:bruno+mars",
      "spotify:search:bruno+mars+lady+gaga",
      "spotify:search:bruno+arias",
      "spotify:search:bruno+mars+exitos"
    ],
    "message_query": "bruno",
    "timestamp_utc": "2025-08-09T21:03:02.695Z",
    "context_time": 1754773382695,
    "message_country": "AR",
    "message_locale": "en_GB",
    "message_platform": "ANDROID_ARM",
    "message_timestamp": 1754773383523,
    "message_top_recs_uris": [
    ],
    "message_user_agent": "Spotify/9.0.68.632 Android/33 (moto g72)"
  },
  {
    "message_candidate_uris": [
      "spotify:playlist:1OC997aDTD3Ji5ZybaV7LV",
      "spotify:playlist:0XdBQNUf7Ng39W2g5hkYvP",
      "spotify:playlist:37i9dQZEVXbMXbN3EUUhlg",
      "spotify:playlist:2TIvNr191G0VJ9Cdmi4A8u",
      "spotify:playlist:1hEdFWtYe5PmxNQKlUJWzL",
      "spotify:track:36SJ7ZFx8J1f1RsewmUwMX",
      "spotify:episode:51O3YC8lOQVRTm3PrE8LcR",
      "spotify:playlist:1As8svArNFfdE7x6XLnZvd",
      "spotify:playlist:6bA0D4xJJ8zQPEs26YnzMb",
      "spotify:track:0c27qjzqEgMLMnWTl5bCU8",
      "spotify:playlist:0cTxwGHW2gQMU6ZKS9xC0h",
      "spotify:track:2iDDnYmaz1HhedjI91fbmp",
      "spotify:playlist:3KWKH0BUvYMEbp2zgOD2l5",
      "spotify:track:4Fp23GGA5WNWgoDjdhBHeK",
      "spotify:artist:25uPlxGvXMDy9eUX7oeDei",
      "spotify:track:4ohps6RKcqCWMfK8GFcYE5",
      "spotify:search:brasilero",
      "spotify:search:brasilerass+famosas",
      "spotify:search:brasile%C3%B1o",
      "spotify:search:brasil"
    ],
    "message_query": "bras",
    "timestamp_utc": "2025-07-25T21:44:21.805Z",
    "context_time": 1753479861805,
    "message_country": "AR",
    "message_locale": "en_GB",
    "message_platform": "ANDROID_ARM",
    "message_timestamp": 1753479860850,
    "message_top_recs_uris": [
    ],
    "message_user_agent": "Spotify/9.0.64.608 Android/33 (moto g72)"
  },
  {
    "message_candidate_uris": [
      "spotify:track:1DIXPcTDzTj8ZMHt3PDt8p",
      "spotify:artist:3qm84nBOXUEQ2vnTfUTTFC",
      "spotify:playlist:0WlumRAOdasJrs51g8wnDZ",
      "spotify:playlist:37i9dQZF1DX11ghcIxjcjE",
      "spotify:playlist:37i9dQZF1DZ06evO1Ziym4",
      "spotify:playlist:5fTsKXMv1IrYraMQ6iHXEL",
      "spotify:artist:1QOmebWGB6FdFtW7Bo3F0W",
      "spotify:artist:3AA28KZvwAUcZuOKwyblJQ",
      "spotify:episode:6b0Bo9ghk2SAOLq5bq5uB3",
      "spotify:playlist:7x48vLNhZqlt98ApMUWsDU",
      "spotify:playlist:22LgD7bUoQLvSRy322OxNp",
      "spotify:artist:7oPftvlwr6VrsViSDV7fJY",
      "spotify:playlist:1r5UEcC7obqJB20WqGHdCe",
      "spotify:playlist:4gUUG6abds6TumnwjU0WzC",
      "spotify:playlist:37i9dQZF1DZ06evO1rzScc",
      "spotify:playlist:1LHaVrIXuUcHLstjKpsxev",
      "spotify:search:guns+n%27+roses",
      "spotify:search:gorillaz",
      "spotify:search:green+day",
      "spotify:search:genesis"
    ],
    "message_query": "g",
    "timestamp_utc": "2025-07-25T21:39:08.216Z",
    "context_time": 1753479548216,
    "message_country": "AR",
    "message_locale": "en_GB",
    "message_platform": "ANDROID_ARM",
    "message_timestamp": 1753479545517,
    "message_top_recs_uris": [
    ],
    "message_user_agent": "Spotify/9.0.64.608 Android/33 (moto g72)"
  },
  {
    "message_candidate_uris": [
      "spotify:artist:1QOmebWGB6FdFtW7Bo3F0W",
      "spotify:playlist:37i9dQZF1DZ06evO12BIac",
      "spotify:playlist:3APf3LJ3lC9ka35T9dJfba",
      "spotify:playlist:37i9dQZF1E4nc6r5XLZ1Yu",
      "spotify:artist:3dOfwznaY7FEKpF8aw1q9i",
      "spotify:track:5wjiZSbxaLyLpGimpwqh1H",
      "spotify:track:1Bov4bMY1IgfOrvUWWbhSe",
      "spotify:track:65DBZofI0b79kfHTcWWDuU",
      "spotify:album:2rIdWbXPjcq8K7BCccBhhC",
      "spotify:playlist:3JlgQTTJxoWQ5nNOVdsBqf",
      "spotify:album:51wepZm3YvZfvFxiu7D5F8",
      "spotify:playlist:2wys4K71I3F6C4puwKImHK",
      "spotify:album:46Yq9oqsaZJb9ahoMk9iVd",
      "spotify:playlist:2TieOXUFdPe8OrB8WYgKJy",
      "spotify:album:75onhE4ne52iMHlVcpHUKR",
      "spotify:playlist:37i9dQZF1EIZwLDpPbvfRp",
      "spotify:search:gustavo+cerati",
      "spotify:search:gustavo+cordera",
      "spotify:search:gustavo+pena",
      "spotify:search:gustavo+pena+el+pr%C3%ADncipe"
    ],
    "message_query": "Gustavo ",
    "timestamp_utc": "2025-07-25T21:39:08.181Z",
    "context_time": 1753479548181,
    "message_country": "AR",
    "message_locale": "en_GB",
    "message_platform": "ANDROID_ARM",
    "message_timestamp": 1753479546801,
    "message_top_recs_uris": [
    ],
    "message_user_agent": "Spotify/9.0.64.608 Android/33 (moto g72)"
  },
  {
    "message_candidate_uris": [
      "spotify:artist:3eqjTLE0HfPfh78zjh6TqT",
      "spotify:artist:0du5cEVh5yTK9QJze8zA0C",
      "spotify:playlist:3IRQehF2IhLczR9kyKDYVA",
      "spotify:playlist:0ikAq4EgRbrgbjSPIgjS8l",
      "spotify:playlist:4UloqXLVxIKJgCNbtWaf69",
      "spotify:artist:1VV61UepOgsPiOjljK6mBY",
      "spotify:artist:7Iffw1nP3NjCWkRIx3Ily9",
      "spotify:artist:26dSoYclwsYLMAKD3tpOr4",
      "spotify:episode:09NOJuCMy7XRIN0oR6zL5D",
      "spotify:track:2plbrEY59IikOBgBGLjaoe",
      "spotify:artist:3Z02hBLubJxuFJfhacLSDc",
      "spotify:playlist:37i9dQZF1E4vTHVDH1FT3Y",
      "spotify:artist:3fMbdgg4jU18AjLCKBhRSm",
      "spotify:artist:7CwJ4VEWs7HV7MWQt9cgyk",
      "spotify:artist:4gzpq5DPGxSnKTe4SA8HAU",
      "spotify:track:5vNRhkKd0yEAg8suGBpjeY",
      "spotify:search:bruno+mars",
      "spotify:search:bruce+springsteen",
      "spotify:search:bruno+mars+lady+gaga",
      "spotify:search:bruce+dickinson"
    ],
    "message_query": "bru",
    "timestamp_utc": "2025-08-09T21:03:02.180Z",
    "context_time": 1754773382180,
    "message_country": "AR",
    "message_locale": "en_GB",
    "message_platform": "ANDROID_ARM",
    "message_timestamp": 1754773382987,
    "message_top_recs_uris": [
    ],
    "message_user_agent": "Spotify/9.0.68.632 Android/33 (moto g72)"
  },
  {
    "message_candidate_uris": [
      "spotify:artist:0du5cEVh5yTK9QJze8zA0C",
      "spotify:track:2plbrEY59IikOBgBGLjaoe",
      "spotify:track:32OlwWuMpZ6b0aN2RZOeMS",
      "spotify:playlist:37i9dQZF1E4vTHVDH1FT3Y",
      "spotify:playlist:37i9dQZF1DZ06evO03DwPK",
      "spotify:playlist:5PQJnqvGTMX5rjR8c7GIkq",
      "spotify:track:3w3y8KPTfNeOKPiqUTakBh",
      "spotify:artist:3fMbdgg4jU18AjLCKBhRSm",
      "spotify:playlist:6x59Uuh8xp32g88XiCiNLY",
      "spotify:playlist:474jn2a57cASJtV2HBpwbx",
      "spotify:track:6b8Be6ljOzmkOmFslEb23P",
      "spotify:episode:09NOJuCMy7XRIN0oR6zL5D",
      "spotify:artist:04gDigrS5kc9YWfZHwBETP",
      "spotify:track:2iuZJX9X9P0GKaE93xcPjk",
      "spotify:track:386RUes7n1uM1yfzgeUuwp",
      "spotify:track:0nJW01T7XtvILxQgC5J7Wh",
      "spotify:search:bruno+mars",
      "spotify:search:bruno+mars+lady+gaga",
      "spotify:search:bruno+mars+exitos",
      "spotify:search:bruno+mars+when+i+was+your+man"
    ],
    "message_query": "Bruno mar",
    "timestamp_utc": "2025-08-09T21:03:04.031Z",
    "context_time": 1754773384031,
    "message_country": "AR",
    "message_locale": "en_GB",
    "message_platform": "ANDROID_ARM",
    "message_timestamp": 1754773384780,
    "message_top_recs_uris": [
    ],
    "message_user_agent": "Spotify/9.0.68.632 Android/33 (moto g72)"
  },
  {
    "message_candidate_uris": [
      "spotify:artist:7bu3H8JO7d0UbMoVzbo70s",
      "spotify:artist:4V8LLVI7PbaPR0K2TGSxFF",
      "spotify:artist:2yEwvVSSSUkcLeSTNyHKh8",
      "spotify:playlist:7gtuV4IuSJLoKGPnGQMMvw",
      "spotify:artist:3yY2gUcIsjMr8hjo51PoJ8",
      "spotify:playlist:37i9dQZEVXbMMy2roB9myp",
      "spotify:artist:5NGO30tJxFlKixkPSgXcFE",
      "spotify:show:3IM0lmZxpFAY7CwMuv9H4g",
      "spotify:artist:22WZ7M8sxp5THdruNY3gXt",
      "spotify:playlist:45v2Mc9tSBDQhtIlf8ETWF",
      "spotify:artist:3WrFJ7ztbogyGnTHbHJFl2",
      "spotify:artist:0Zncosr79q01riJYbSBNA1",
      "spotify:artist:4lxfqrEsLX6N1N4OCSkILp",
      "spotify:playlist:6z1ISkBcTG6qYsQfbWzM1j",
      "spotify:artist:0epOFNiUfyON9EYx7Tpr6V",
      "spotify:artist:22bE4uQ6baNwSHPVcDxLCe",
      "spotify:search:tu+misterioso+alguien",
      "spotify:search:the+beatles",
      "spotify:search:tan+bionica",
      "spotify:search:turf"
    ],
    "message_query": "t",
    "timestamp_utc": "2025-08-09T15:34:24.176Z",
    "context_time": 1754753664176,
    "message_country": "AR",
    "message_locale": "en_GB",
    "message_platform": "ANDROID_ARM",
    "message_timestamp": 1754753664946,
    "message_top_recs_uris": [
    ],
    "message_user_agent": "Spotify/9.0.68.632 Android/33 (moto g72)"
  },
  {
    "message_candidate_uris": [
      "spotify:track:0zZnBbRW4Dt4cJKVtUQFwF",
      "spotify:artist:7MiDcPa6UiV3In7lIM71IN",
      "spotify:track:0INaMqjJJe1BZpnWuCxDzt",
      "spotify:playlist:1OC997aDTD3Ji5ZybaV7LV",
      "spotify:playlist:30Z5afhQY1bz0ONmO76DGB",
      "spotify:playlist:2PY7eEcSWukU56dgHdz771",
      "spotify:playlist:1QY3gV9Ihkz8FBTpNbfVxC",
      "spotify:playlist:01kCJyJWmoyIlIU2LUlxGf",
      "spotify:track:6xepovPqjvrkEw9Y5AMmTm",
      "spotify:playlist:2TIvNr191G0VJ9Cdmi4A8u",
      "spotify:track:1XdVkLDSTk6cM3SEP5v8Bs",
      "spotify:playlist:1hEdFWtYe5PmxNQKlUJWzL",
      "spotify:playlist:0cTxwGHW2gQMU6ZKS9xC0h",
      "spotify:track:5xYsacjSZrSYJQDacIs0tq",
      "spotify:track:36SJ7ZFx8J1f1RsewmUwMX",
      "spotify:track:1K8AtBJXcdq5mywMnZuARP",
      "spotify:search:gustavo+lima",
      "spotify:search:gusttavo+lima",
      "spotify:search:gusttavo+lima+balada+tch%C3%AA+tcherere+tch%C3%AA+tch%C3%AA+gustavo+lima",
      "spotify:search:gusttavo+lima+balada+ao+vivo"
    ],
    "message_query": "Gustavo lima",
    "timestamp_utc": "2025-07-25T21:44:06.125Z",
    "context_time": 1753479846125,
    "message_country": "AR",
    "message_locale": "en_GB",
    "message_platform": "ANDROID_ARM",
    "message_timestamp": 1753479845194,
    "message_top_recs_uris": [
    ],
    "message_user_agent": "Spotify/9.0.64.608 Android/33 (moto g72)"
  },
  {
    "message_candidate_uris": [
      "spotify:track:1DIXPcTDzTj8ZMHt3PDt8p",
      "spotify:artist:6S0GHTqz5sxK5f9HtLXn9q",
      "spotify:playlist:0WlumRAOdasJrs51g8wnDZ",
      "spotify:artist:3qm84nBOXUEQ2vnTfUTTFC",
      "spotify:playlist:37i9dQZF1DX11ghcIxjcjE",
      "spotify:artist:072qmH2ykeCEmQfp5qDqT1",
      "spotify:playlist:37i9dQZF1DZ06evO1Ziym4",
      "spotify:playlist:5fTsKXMv1IrYraMQ6iHXEL",
      "spotify:artist:1QOmebWGB6FdFtW7Bo3F0W",
      "spotify:artist:3AA28KZvwAUcZuOKwyblJQ",
      "spotify:track:1W7vRnl4LcjJztqj8s3UoJ",
      "spotify:track:7oDDV1cal0M0RIjr4HuuJ9",
      "spotify:playlist:7x48vLNhZqlt98ApMUWsDU",
      "spotify:playlist:22LgD7bUoQLvSRy322OxNp",
      "spotify:artist:7oPftvlwr6VrsViSDV7fJY",
      "spotify:playlist:1r5UEcC7obqJB20WqGHdCe",
      "spotify:search:guns+n%27+roses",
      "spotify:search:garbage",
      "spotify:search:gustavo+cerati",
      "spotify:search:gorillaz"
    ],
    "message_query": "g",
    "timestamp_utc": "2025-07-25T21:44:02.553Z",
    "context_time": 1753479842553,
    "message_country": "AR",
    "message_locale": "en_GB",
    "message_platform": "ANDROID_ARM",
    "message_timestamp": 1753479841629,
    "message_top_recs_uris": [
    ],
    "message_user_agent": "Spotify/9.0.64.608 Android/33 (moto g72)"
  },
  {
    "message_candidate_uris": [
      "spotify:playlist:1msY3c9fzgE3V11aNhsq2O",
      "spotify:playlist:2bairK0EAgiZy6W2tjw2UV",
      "spotify:playlist:37i9dQZF1DWZ2DWnNKZTXs",
      "spotify:playlist:1OC997aDTD3Ji5ZybaV7LV",
      "spotify:playlist:3m1ar1Cz9v7JJqFVP6HNXT",
      "spotify:episode:3NbdXLtfWVXT5OoB2cxixh",
      "spotify:playlist:1hEdFWtYe5PmxNQKlUJWzL",
      "spotify:playlist:37i9dQZEVXbMXbN3EUUhlg",
      "spotify:track:6i2kn3iS5WKzsaYBdeHLIQ",
      "spotify:playlist:0XdBQNUf7Ng39W2g5hkYvP",
      "spotify:playlist:0WmbfhNdbVSp9Qqb3GM3FT",
      "spotify:playlist:3b1OB14lWIMPHDQ2Rvjtme",
      "spotify:playlist:2TIvNr191G0VJ9Cdmi4A8u",
      "spotify:track:1PCvKFPWnTXAe2oaReVUcr",
      "spotify:playlist:36EVuywkYuJLsQfOZ2HU4X",
      "spotify:track:36SJ7ZFx8J1f1RsewmUwMX",
      "spotify:search:brasil+2025",
      "spotify:search:brasil+2025+as+melhores+e+mais+tocadas",
      "spotify:search:brasilerass+famosas",
      "spotify:search:brasil+2014"
    ],
    "message_query": "Brasil 20",
    "timestamp_utc": "2025-07-25T21:44:23.687Z",
    "context_time": 1753479863687,
    "message_country": "AR",
    "message_locale": "en_GB",
    "message_platform": "ANDROID_ARM",
    "message_timestamp": 1753479862777,
    "message_top_recs_uris": [
    ],
    "message_user_agent": "Spotify/9.0.64.608 Android/33 (moto g72)"
  },
  {
    "message_candidate_uris": [
      "spotify:playlist:1OC997aDTD3Ji5ZybaV7LV",
      "spotify:playlist:37i9dQZEVXbMXbN3EUUhlg",
      "spotify:playlist:0XdBQNUf7Ng39W2g5hkYvP",
      "spotify:playlist:1hEdFWtYe5PmxNQKlUJWzL",
      "spotify:playlist:6bA0D4xJJ8zQPEs26YnzMb",
      "spotify:track:36SJ7ZFx8J1f1RsewmUwMX",
      "spotify:playlist:0cTxwGHW2gQMU6ZKS9xC0h",
      "spotify:playlist:2TIvNr191G0VJ9Cdmi4A8u",
      "spotify:playlist:3KWKH0BUvYMEbp2zgOD2l5",
      "spotify:playlist:1msY3c9fzgE3V11aNhsq2O",
      "spotify:track:4ohps6RKcqCWMfK8GFcYE5",
      "spotify:track:2iDDnYmaz1HhedjI91fbmp",
      "spotify:track:0c27qjzqEgMLMnWTl5bCU8",
      "spotify:playlist:78xhpWhXna83q0CCkyouaJ",
      "spotify:track:0yGeZidghwNVJmLHmAEiNY",
      "spotify:playlist:3th5U546Sl0hAYWq3lGYFP",
      "spotify:search:brasilerass+famosas",
      "spotify:search:brazilian+music",
      "spotify:search:brasil+2025+as+melhores+e+mais+tocadas",
      "spotify:search:brasil+2025"
    ],
    "message_query": "Brasil ",
    "timestamp_utc": "2025-07-25T21:44:22.149Z",
    "context_time": 1753479862149,
    "message_country": "AR",
    "message_locale": "en_GB",
    "message_platform": "ANDROID_ARM",
    "message_timestamp": 1753479861211,
    "message_top_recs_uris": [
    ],
    "message_user_agent": "Spotify/9.0.64.608 Android/33 (moto g72)"
  },
  {
    "message_candidate_uris": [
      "spotify:artist:1QOmebWGB6FdFtW7Bo3F0W",
      "spotify:playlist:37i9dQZF1DZ06evO12BIac",
      "spotify:playlist:37i9dQZF1E4nc6r5XLZ1Yu",
      "spotify:playlist:3APf3LJ3lC9ka35T9dJfba",
      "spotify:artist:3dOfwznaY7FEKpF8aw1q9i",
      "spotify:artist:7An4yvF7hDYDolN4m5zKBp",
      "spotify:album:51wepZm3YvZfvFxiu7D5F8",
      "spotify:album:46Yq9oqsaZJb9ahoMk9iVd",
      "spotify:track:5wjiZSbxaLyLpGimpwqh1H",
      "spotify:album:2rIdWbXPjcq8K7BCccBhhC",
      "spotify:playlist:37i9dQZF1EIZwLDpPbvfRp",
      "spotify:track:1Bov4bMY1IgfOrvUWWbhSe",
      "spotify:playlist:2TieOXUFdPe8OrB8WYgKJy",
      "spotify:album:75onhE4ne52iMHlVcpHUKR",
      "spotify:track:65DBZofI0b79kfHTcWWDuU",
      "spotify:playlist:2wys4K71I3F6C4puwKImHK",
      "spotify:search:gustavo+cerati",
      "spotify:search:gustavo+cordera",
      "spotify:search:gustavo+pena+el+pr%C3%ADncipe",
      "spotify:search:gustavo+pena"
    ],
    "message_query": "gusta",
    "timestamp_utc": "2025-07-25T21:39:08.154Z",
    "context_time": 1753479548154,
    "message_country": "AR",
    "message_locale": "en_GB",
    "message_platform": "ANDROID_ARM",
    "message_timestamp": 1753479546423,
    "message_top_recs_uris": [
    ],
    "message_user_agent": "Spotify/9.0.64.608 Android/33 (moto g72)"
  },
  {
    "message_candidate_uris": [
      "spotify:track:0zZnBbRW4Dt4cJKVtUQFwF",
      "spotify:artist:7MiDcPa6UiV3In7lIM71IN",
      "spotify:track:0INaMqjJJe1BZpnWuCxDzt",
      "spotify:playlist:1OC997aDTD3Ji5ZybaV7LV",
      "spotify:playlist:30Z5afhQY1bz0ONmO76DGB",
      "spotify:playlist:2PY7eEcSWukU56dgHdz771",
      "spotify:playlist:1QY3gV9Ihkz8FBTpNbfVxC",
      "spotify:playlist:01kCJyJWmoyIlIU2LUlxGf",
      "spotify:track:6xepovPqjvrkEw9Y5AMmTm",
      "spotify:playlist:2TIvNr191G0VJ9Cdmi4A8u",
      "spotify:track:1XdVkLDSTk6cM3SEP5v8Bs",
      "spotify:playlist:1hEdFWtYe5PmxNQKlUJWzL",
      "spotify:playlist:0cTxwGHW2gQMU6ZKS9xC0h",
      "spotify:track:5xYsacjSZrSYJQDacIs0tq",
      "spotify:track:36SJ7ZFx8J1f1RsewmUwMX",
      "spotify:track:1K8AtBJXcdq5mywMnZuARP",
      "spotify:search:gustavo+lima",
      "spotify:search:gusttavo+lima",
      "spotify:search:gusttavo+lima+balada+tch%C3%AA+tcherere+tch%C3%AA+tch%C3%AA+gustavo+lima",
      "spotify:search:gusttavo+lima+balada+ao+vivo"
    ],
    "message_query": "Gustavo lima",
    "timestamp_utc": "2025-07-25T21:39:09.403Z",
    "context_time": 1753479549403,
    "message_country": "AR",
    "message_locale": "en_GB",
    "message_platform": "ANDROID_ARM",
    "message_timestamp": 1753479548427,
    "message_top_recs_uris": [
    ],
    "message_user_agent": "Spotify/9.0.64.608 Android/33 (moto g72)"
  },
  {
    "message_candidate_uris": [
      "spotify:artist:3qm84nBOXUEQ2vnTfUTTFC",
      "spotify:artist:1QOmebWGB6FdFtW7Bo3F0W",
      "spotify:playlist:37i9dQZF1DZ06evO1Ziym4",
      "spotify:playlist:37i9dQZF1DZ06evO1rzScc",
      "spotify:playlist:22LgD7bUoQLvSRy322OxNp",
      "spotify:playlist:37i9dQZF1DZ06evO12BIac",
      "spotify:episode:1lFvSSkO4VDPVUK7AwGQBQ",
      "spotify:playlist:61AuftDk6G9CV0t1OuHAEc",
      "spotify:playlist:5htTCXmpYg3czvFZXIQkrP",
      "spotify:playlist:2ZONg885GRx1XlgcsNVzLk",
      "spotify:track:2yoPmaL4ckJ5CI6oRtLEir",
      "spotify:playlist:7bsHHU5RGk9L1ifUKc8PeD",
      "spotify:playlist:3edtw06fcs0gDxWX7jyTCn",
      "spotify:playlist:3APf3LJ3lC9ka35T9dJfba",
      "spotify:track:0hVHEfyv50IWtTzEvxJl4Z",
      "spotify:playlist:4jmjLUUxvtSgHi4JZCctHU",
      "spotify:search:guns+n%27+roses",
      "spotify:search:gustavo+cerati",
      "spotify:search:guasones",
      "spotify:search:guano+apes+dreamin%27"
    ],
    "message_query": "gu",
    "timestamp_utc": "2025-07-25T21:44:02.714Z",
    "context_time": 1753479842714,
    "message_country": "AR",
    "message_locale": "en_GB",
    "message_platform": "ANDROID_ARM",
    "message_timestamp": 1753479841814,
    "message_top_recs_uris": [
    ],
    "message_user_agent": "Spotify/9.0.64.608 Android/33 (moto g72)"
  },
  {
    "message_candidate_uris": [
      "spotify:artist:0du5cEVh5yTK9QJze8zA0C",
      "spotify:track:2plbrEY59IikOBgBGLjaoe",
      "spotify:episode:09NOJuCMy7XRIN0oR6zL5D",
      "spotify:playlist:37i9dQZF1DZ06evO03DwPK",
      "spotify:track:5vNRhkKd0yEAg8suGBpjeY",
      "spotify:artist:3fMbdgg4jU18AjLCKBhRSm",
      "spotify:playlist:5PQJnqvGTMX5rjR8c7GIkq",
      "spotify:playlist:37i9dQZF1E4vTHVDH1FT3Y",
      "spotify:artist:4gzpq5DPGxSnKTe4SA8HAU",
      "spotify:track:32OlwWuMpZ6b0aN2RZOeMS",
      "spotify:artist:59OheJsvimLlXWvuL9j7Df",
      "spotify:artist:1HY2Jd0NmPuamShAr6KMms",
      "spotify:artist:3tDix7cw0fgoa5idDGJ6Wo",
      "spotify:artist:5JXhkyafynxCvxtov7C1PV",
      "spotify:artist:04gDigrS5kc9YWfZHwBETP",
      "spotify:playlist:474jn2a57cASJtV2HBpwbx",
      "spotify:search:bruno+mars",
      "spotify:search:bruno+mars+lady+gaga",
      "spotify:search:bruno+arias",
      "spotify:search:bruno+mars+exitos"
    ],
    "message_query": "brun",
    "timestamp_utc": "2025-08-09T21:03:02.446Z",
    "context_time": 1754773382446,
    "message_country": "AR",
    "message_locale": "en_GB",
    "message_platform": "ANDROID_ARM",
    "message_timestamp": 1754773383279,
    "message_top_recs_uris": [
    ],
    "message_user_agent": "Spotify/9.0.68.632 Android/33 (moto g72)"
  }
]